{
 "nodes": [
  {
   "id": "Potri.015G124500", 
   "clusters": {
    "0": 0, 
    "4.8": 0, 
    "2.0": 0, 
    "6.0": 0, 
    "4.0": 0, 
    "0.8": 0, 
    "1.6": 0, 
    "3.2": 0, 
    "2.4": 0, 
    "1.2": 0, 
    "0.4": 0, 
    "6.8": 0, 
    "7.2": 0, 
    "8.0": 0, 
    "7.6": 0, 
    "3.6": 0, 
    "6.4": 0, 
    "5.2": 0, 
    "2.8": 0, 
    "5.6": 0, 
    "4.4": 0
   }, 
   "species": "pt", 
   "plaza_name": "PT15G12450", 
   "anchor": 0
  }, 
  {
   "id": "Phpat.001G023700", 
   "clusters": {
    "0": 0, 
    "4.8": 0, 
    "2.0": 0, 
    "6.0": 0, 
    "4.0": 0, 
    "0.8": 0, 
    "1.6": 0, 
    "3.2": 0, 
    "2.4": 0, 
    "1.2": 0, 
    "0.4": 0, 
    "6.8": 0, 
    "7.2": 0, 
    "8.0": 0, 
    "7.6": 0, 
    "3.6": 0, 
    "6.4": 0, 
    "5.2": 0, 
    "2.8": 0, 
    "5.6": 0, 
    "4.4": 0
   }, 
   "species": "ph", 
   "plaza_name": "PP00045G01210", 
   "anchor": 0
  }, 
  {
   "id": "Medtr3g014450", 
   "clusters": {
    "0": 0, 
    "4.8": 0, 
    "2.0": 0, 
    "6.0": 0, 
    "4.0": 0, 
    "0.8": 0, 
    "1.6": 0, 
    "3.2": 0, 
    "2.4": 0, 
    "1.2": 0, 
    "0.4": 0, 
    "6.8": 0, 
    "7.2": 0, 
    "8.0": 0, 
    "7.6": 0, 
    "3.6": 0, 
    "6.4": 0, 
    "5.2": 0, 
    "2.8": 0, 
    "5.6": 0, 
    "4.4": 0
   }, 
   "species": "mt", 
   "plaza_name": "MT3G014450", 
   "anchor": 0
  }, 
  {
   "id": "52317.m000020", 
   "clusters": {
    "0": 0, 
    "4.8": 0, 
    "2.0": 0, 
    "6.0": 0, 
    "4.0": 0, 
    "0.8": 0, 
    "1.6": 0, 
    "3.2": 0, 
    "2.4": 0, 
    "1.2": 0, 
    "0.4": 0, 
    "6.8": 0, 
    "7.2": 0, 
    "8.0": 0, 
    "7.6": 0, 
    "3.6": 0, 
    "6.4": 0, 
    "5.2": 0, 
    "2.8": 0, 
    "5.6": 0, 
    "4.4": 0
   }, 
   "species": "rc", 
   "plaza_name": "RC52317G00010", 
   "anchor": 0
  }, 
  {
   "id": "MDP0000462973", 
   "clusters": {
    "0": 0, 
    "4.8": 0, 
    "2.0": 0, 
    "6.0": 0, 
    "4.0": 0, 
    "0.8": 0, 
    "1.6": 0, 
    "3.2": 0, 
    "2.4": 0, 
    "1.2": 0, 
    "0.4": 0, 
    "6.8": 0, 
    "7.2": 0, 
    "8.0": 0, 
    "7.6": 0, 
    "3.6": 0, 
    "6.4": 0, 
    "5.2": 0, 
    "2.8": 0, 
    "5.6": 0, 
    "4.4": 0
   }, 
   "species": "md", 
   "plaza_name": "MD00G011430", 
   "anchor": 0
  }, 
  {
   "id": "AT2G35110", 
   "clusters": {
    "0": 1, 
    "4.8": 3, 
    "2.0": 3, 
    "6.0": 3, 
    "4.0": 3, 
    "0.8": 1, 
    "1.6": 3, 
    "3.2": 3, 
    "2.4": 3, 
    "1.2": 1, 
    "0.4": 1, 
    "6.8": 3, 
    "7.2": 3, 
    "8.0": 3, 
    "7.6": 3, 
    "3.6": 3, 
    "6.4": 3, 
    "5.2": 3, 
    "2.8": 3, 
    "5.6": 3, 
    "4.4": 3
   }, 
   "species": "at", 
   "plaza_name": "AT2G35110", 
   "anchor": 0
  }, 
  {
   "id": "GRMZM2G447432", 
   "clusters": {
    "0": 0, 
    "4.8": 0, 
    "2.0": 0, 
    "6.0": 0, 
    "4.0": 0, 
    "0.8": 0, 
    "1.6": 0, 
    "3.2": 0, 
    "2.4": 0, 
    "1.2": 0, 
    "0.4": 0, 
    "6.8": 0, 
    "7.2": 0, 
    "8.0": 0, 
    "7.6": 0, 
    "3.6": 0, 
    "6.4": 0, 
    "5.2": 0, 
    "2.8": 0, 
    "5.6": 0, 
    "4.4": 0
   }, 
   "species": "zm", 
   "plaza_name": "ZM02G36720", 
   "anchor": 0
  }, 
  {
   "id": "Medtr4g084140", 
   "clusters": {
    "0": 1, 
    "4.8": 2, 
    "2.0": 2, 
    "6.0": 2, 
    "4.0": 2, 
    "0.8": 1, 
    "1.6": 2, 
    "3.2": 2, 
    "2.4": 2, 
    "1.2": 1, 
    "0.4": 1, 
    "6.8": 2, 
    "7.2": 2, 
    "8.0": 2, 
    "7.6": 2, 
    "3.6": 2, 
    "6.4": 2, 
    "5.2": 2, 
    "2.8": 2, 
    "5.6": 2, 
    "4.4": 2
   }, 
   "species": "mt", 
   "plaza_name": "MT4G084140", 
   "anchor": 1
  }, 
  {
   "id": "Glyma.07G221000", 
   "clusters": {
    "0": 1, 
    "4.8": 2, 
    "2.0": 2, 
    "6.0": 2, 
    "4.0": 2, 
    "0.8": 1, 
    "1.6": 2, 
    "3.2": 2, 
    "2.4": 2, 
    "1.2": 1, 
    "0.4": 1, 
    "6.8": 2, 
    "7.2": 2, 
    "8.0": 2, 
    "7.6": 2, 
    "3.6": 2, 
    "6.4": 2, 
    "5.2": 2, 
    "2.8": 2, 
    "5.6": 2, 
    "4.4": 2
   }, 
   "species": "gm", 
   "plaza_name": "GM07G34620", 
   "anchor": 0
  }, 
  {
   "id": "LOC_Os08g43130", 
   "clusters": {
    "0": 0, 
    "4.8": 0, 
    "2.0": 0, 
    "6.0": 0, 
    "4.0": 0, 
    "0.8": 0, 
    "1.6": 0, 
    "3.2": 0, 
    "2.4": 0, 
    "1.2": 0, 
    "0.4": 0, 
    "6.8": 0, 
    "7.2": 0, 
    "8.0": 0, 
    "7.6": 0, 
    "3.6": 0, 
    "6.4": 0, 
    "5.2": 0, 
    "2.8": 0, 
    "5.6": 0, 
    "4.4": 0
   }, 
   "species": "os", 
   "plaza_name": "OS08G43130", 
   "anchor": 0
  }, 
  {
   "id": "MDP0000003818", 
   "clusters": {
    "0": 0, 
    "4.8": 0, 
    "2.0": 0, 
    "6.0": 0, 
    "4.0": 0, 
    "0.8": 0, 
    "1.6": 0, 
    "3.2": 0, 
    "2.4": 0, 
    "1.2": 0, 
    "0.4": 0, 
    "6.8": 0, 
    "7.2": 0, 
    "8.0": 0, 
    "7.6": 0, 
    "3.6": 0, 
    "6.4": 0, 
    "5.2": 0, 
    "2.8": 0, 
    "5.6": 0, 
    "4.4": 0
   }, 
   "species": "md", 
   "plaza_name": "MD05G008900", 
   "anchor": 0
  }, 
  {
   "id": "Phpat.011G004300", 
   "clusters": {
    "0": 0, 
    "4.8": 0, 
    "2.0": 0, 
    "6.0": 0, 
    "4.0": 0, 
    "0.8": 0, 
    "1.6": 0, 
    "3.2": 0, 
    "2.4": 0, 
    "1.2": 0, 
    "0.4": 0, 
    "6.8": 0, 
    "7.2": 0, 
    "8.0": 0, 
    "7.6": 0, 
    "3.6": 0, 
    "6.4": 0, 
    "5.2": 0, 
    "2.8": 0, 
    "5.6": 0, 
    "4.4": 0
   }, 
   "species": "ph", 
   "plaza_name": "PP00039G00580", 
   "anchor": 0
  }, 
  {
   "id": "Solyc02g068720.2", 
   "clusters": {
    "0": 1, 
    "4.8": 1, 
    "2.0": 1, 
    "6.0": 1, 
    "4.0": 1, 
    "0.8": 1, 
    "1.6": 1, 
    "3.2": 1, 
    "2.4": 1, 
    "1.2": 1, 
    "0.4": 1, 
    "6.8": 1, 
    "7.2": 1, 
    "8.0": 1, 
    "7.6": 1, 
    "3.6": 1, 
    "6.4": 1, 
    "5.2": 1, 
    "2.8": 1, 
    "5.6": 1, 
    "4.4": 1
   }, 
   "species": "sl", 
   "plaza_name": "ST02G014880", 
   "anchor": 0
  }, 
  {
   "id": "MDP0000128017", 
   "clusters": {
    "0": 0, 
    "4.8": 0, 
    "2.0": 0, 
    "6.0": 0, 
    "4.0": 0, 
    "0.8": 0, 
    "1.6": 0, 
    "3.2": 0, 
    "2.4": 0, 
    "1.2": 0, 
    "0.4": 0, 
    "6.8": 0, 
    "7.2": 0, 
    "8.0": 0, 
    "7.6": 0, 
    "3.6": 0, 
    "6.4": 0, 
    "5.2": 0, 
    "2.8": 0, 
    "5.6": 0, 
    "4.4": 0
   }, 
   "species": "md", 
   "plaza_name": "MD00G325620", 
   "anchor": 0
  }, 
  {
   "id": "scaffold00062.200", 
   "clusters": {
    "0": 0, 
    "4.8": 0, 
    "2.0": 0, 
    "6.0": 0, 
    "4.0": 0, 
    "0.8": 0, 
    "1.6": 0, 
    "3.2": 0, 
    "2.4": 0, 
    "1.2": 0, 
    "0.4": 0, 
    "6.8": 0, 
    "7.2": 0, 
    "8.0": 0, 
    "7.6": 0, 
    "3.6": 0, 
    "6.4": 0, 
    "5.2": 0, 
    "2.8": 0, 
    "5.6": 0, 
    "4.4": 0
   }, 
   "species": "ar", 
   "plaza_name": "ATR_00062G01990", 
   "anchor": 0
  }, 
  {
   "id": "MDP0000443324", 
   "clusters": {
    "0": 0, 
    "4.8": 0, 
    "2.0": 0, 
    "6.0": 0, 
    "4.0": 0, 
    "0.8": 0, 
    "1.6": 0, 
    "3.2": 0, 
    "2.4": 0, 
    "1.2": 0, 
    "0.4": 0, 
    "6.8": 0, 
    "7.2": 0, 
    "8.0": 0, 
    "7.6": 0, 
    "3.6": 0, 
    "6.4": 0, 
    "5.2": 0, 
    "2.8": 0, 
    "5.6": 0, 
    "4.4": 0
   }, 
   "species": "md", 
   "plaza_name": "PPE_004G10030", 
   "anchor": 0
  }, 
  {
   "id": "GRMZM2G089565", 
   "clusters": {
    "0": 0, 
    "4.8": 0, 
    "2.0": 0, 
    "6.0": 0, 
    "4.0": 0, 
    "0.8": 0, 
    "1.6": 0, 
    "3.2": 0, 
    "2.4": 0, 
    "1.2": 0, 
    "0.4": 0, 
    "6.8": 0, 
    "7.2": 0, 
    "8.0": 0, 
    "7.6": 0, 
    "3.6": 0, 
    "6.4": 0, 
    "5.2": 0, 
    "2.8": 0, 
    "5.6": 0, 
    "4.4": 0
   }, 
   "species": "zm", 
   "plaza_name": "ZM10G00200", 
   "anchor": 0
  }, 
  {
   "id": "Potri.015G123500", 
   "clusters": {
    "0": 0, 
    "4.8": 0, 
    "2.0": 0, 
    "6.0": 0, 
    "4.0": 0, 
    "0.8": 0, 
    "1.6": 0, 
    "3.2": 0, 
    "2.4": 0, 
    "1.2": 0, 
    "0.4": 0, 
    "6.8": 0, 
    "7.2": 0, 
    "8.0": 0, 
    "7.6": 0, 
    "3.6": 0, 
    "6.4": 0, 
    "5.2": 0, 
    "2.8": 0, 
    "5.6": 0, 
    "4.4": 0
   }, 
   "species": "pt", 
   "plaza_name": "PT15G12350", 
   "anchor": 0
  }, 
  {
   "id": "MDP0000119653", 
   "clusters": {
    "0": 0, 
    "4.8": 0, 
    "2.0": 0, 
    "6.0": 0, 
    "4.0": 0, 
    "0.8": 0, 
    "1.6": 0, 
    "3.2": 0, 
    "2.4": 0, 
    "1.2": 0, 
    "0.4": 0, 
    "6.8": 0, 
    "7.2": 0, 
    "8.0": 0, 
    "7.6": 0, 
    "3.6": 0, 
    "6.4": 0, 
    "5.2": 0, 
    "2.8": 0, 
    "5.6": 0, 
    "4.4": 0
   }, 
   "species": "md", 
   "plaza_name": "MD14G004380", 
   "anchor": 0
  }, 
  {
   "id": "Potri.015G123000", 
   "clusters": {
    "0": 1, 
    "4.8": 1, 
    "2.0": 1, 
    "6.0": 1, 
    "4.0": 1, 
    "0.8": 1, 
    "1.6": 1, 
    "3.2": 1, 
    "2.4": 1, 
    "1.2": 1, 
    "0.4": 1, 
    "6.8": 1, 
    "7.2": 1, 
    "8.0": 1, 
    "7.6": 1, 
    "3.6": 1, 
    "6.4": 1, 
    "5.2": 1, 
    "2.8": 1, 
    "5.6": 1, 
    "4.4": 1
   }, 
   "species": "pt", 
   "plaza_name": "PT15G12300", 
   "anchor": 0
  }, 
  {
   "id": "Thecc1EG006054", 
   "clusters": {
    "0": 1, 
    "4.8": 1, 
    "2.0": 1, 
    "6.0": 1, 
    "4.0": 1, 
    "0.8": 1, 
    "1.6": 1, 
    "3.2": 1, 
    "2.4": 1, 
    "1.2": 1, 
    "0.4": 1, 
    "6.8": 1, 
    "7.2": 1, 
    "8.0": 1, 
    "7.6": 1, 
    "3.6": 1, 
    "6.4": 1, 
    "5.2": 1, 
    "2.8": 1, 
    "5.6": 1, 
    "4.4": 1
   }, 
   "species": "ta", 
   "plaza_name": "TC0002G00830", 
   "anchor": 0
  }, 
  {
   "id": "Potri.015G124200", 
   "clusters": {
    "0": 0, 
    "4.8": 0, 
    "2.0": 0, 
    "6.0": 0, 
    "4.0": 0, 
    "0.8": 0, 
    "1.6": 0, 
    "3.2": 0, 
    "2.4": 0, 
    "1.2": 0, 
    "0.4": 0, 
    "6.8": 0, 
    "7.2": 0, 
    "8.0": 0, 
    "7.6": 0, 
    "3.6": 0, 
    "6.4": 0, 
    "5.2": 0, 
    "2.8": 0, 
    "5.6": 0, 
    "4.4": 0
   }, 
   "species": "pt", 
   "plaza_name": "PT15G12420", 
   "anchor": 0
  }, 
  {
   "id": "Brara.E00925", 
   "clusters": {
    "0": 1, 
    "4.8": 3, 
    "2.0": 3, 
    "6.0": 3, 
    "4.0": 3, 
    "0.8": 1, 
    "1.6": 3, 
    "3.2": 3, 
    "2.4": 3, 
    "1.2": 1, 
    "0.4": 1, 
    "6.8": 3, 
    "7.2": 3, 
    "8.0": 3, 
    "7.6": 3, 
    "3.6": 3, 
    "6.4": 3, 
    "5.2": 3, 
    "2.8": 3, 
    "5.6": 3, 
    "4.4": 3
   }, 
   "species": "br", 
   "plaza_name": "BR05G09540", 
   "anchor": 0
  }, 
  {
   "id": "Potri.015G123900", 
   "clusters": {
    "0": 1, 
    "4.8": 2, 
    "2.0": 2, 
    "6.0": 2, 
    "4.0": 2, 
    "0.8": 1, 
    "1.6": 2, 
    "3.2": 2, 
    "2.4": 2, 
    "1.2": 1, 
    "0.4": 1, 
    "6.8": 2, 
    "7.2": 2, 
    "8.0": 2, 
    "7.6": 2, 
    "3.6": 2, 
    "6.4": 2, 
    "5.2": 2, 
    "2.8": 2, 
    "5.6": 2, 
    "4.4": 2
   }, 
   "species": "pt", 
   "plaza_name": "PT15G12390", 
   "anchor": 0
  }, 
  {
   "id": "evm.TU.supercontig_30.140", 
   "clusters": {
    "0": 1, 
    "4.8": 1, 
    "2.0": 1, 
    "6.0": 1, 
    "4.0": 1, 
    "0.8": 1, 
    "1.6": 1, 
    "3.2": 1, 
    "2.4": 1, 
    "1.2": 1, 
    "0.4": 1, 
    "6.8": 1, 
    "7.2": 1, 
    "8.0": 1, 
    "7.6": 1, 
    "3.6": 1, 
    "6.4": 1, 
    "5.2": 1, 
    "2.8": 1, 
    "5.6": 1, 
    "4.4": 1
   }, 
   "species": "cp", 
   "plaza_name": "CP00030G01400", 
   "anchor": 0
  }, 
  {
   "id": "Gorai.002G164100", 
   "clusters": {
    "0": 0, 
    "4.8": 0, 
    "2.0": 0, 
    "6.0": 0, 
    "4.0": 0, 
    "0.8": 0, 
    "1.6": 0, 
    "3.2": 0, 
    "2.4": 0, 
    "1.2": 0, 
    "0.4": 0, 
    "6.8": 0, 
    "7.2": 0, 
    "8.0": 0, 
    "7.6": 0, 
    "3.6": 0, 
    "6.4": 0, 
    "5.2": 0, 
    "2.8": 0, 
    "5.6": 0, 
    "4.4": 0
   }, 
   "species": "gr", 
   "plaza_name": "GR02G16410", 
   "anchor": 0
  }, 
  {
   "id": "Medtr4g081610", 
   "clusters": {
    "0": 0, 
    "4.8": 0, 
    "2.0": 0, 
    "6.0": 0, 
    "4.0": 0, 
    "0.8": 0, 
    "1.6": 0, 
    "3.2": 0, 
    "2.4": 0, 
    "1.2": 0, 
    "0.4": 0, 
    "6.8": 0, 
    "7.2": 0, 
    "8.0": 0, 
    "7.6": 0, 
    "3.6": 0, 
    "6.4": 0, 
    "5.2": 0, 
    "2.8": 0, 
    "5.6": 0, 
    "4.4": 0
   }, 
   "species": "mt", 
   "plaza_name": "MT4G081610", 
   "anchor": 0
  }, 
  {
   "id": "GRMZM5G886363", 
   "clusters": {
    "0": 0, 
    "4.8": 0, 
    "2.0": 0, 
    "6.0": 0, 
    "4.0": 0, 
    "0.8": 0, 
    "1.6": 0, 
    "3.2": 0, 
    "2.4": 0, 
    "1.2": 0, 
    "0.4": 0, 
    "6.8": 0, 
    "7.2": 0, 
    "8.0": 0, 
    "7.6": 0, 
    "3.6": 0, 
    "6.4": 0, 
    "5.2": 0, 
    "2.8": 0, 
    "5.6": 0, 
    "4.4": 0
   }, 
   "species": "zm", 
   "plaza_name": "ZM10G00440", 
   "anchor": 0
  }, 
  {
   "id": "Glyma.20G019300", 
   "clusters": {
    "0": 1, 
    "4.8": 2, 
    "2.0": 2, 
    "6.0": 2, 
    "4.0": 2, 
    "0.8": 1, 
    "1.6": 2, 
    "3.2": 2, 
    "2.4": 2, 
    "1.2": 1, 
    "0.4": 1, 
    "6.8": 2, 
    "7.2": 2, 
    "8.0": 2, 
    "7.6": 2, 
    "3.6": 2, 
    "6.4": 2, 
    "5.2": 2, 
    "2.8": 2, 
    "5.6": 2, 
    "4.4": 2
   }, 
   "species": "gm", 
   "plaza_name": "GM20G02370", 
   "anchor": 0
  }, 
  {
   "id": "mrna20021", 
   "clusters": {
    "0": 1, 
    "4.8": 1, 
    "2.0": 1, 
    "6.0": 1, 
    "4.0": 1, 
    "0.8": 1, 
    "1.6": 1, 
    "3.2": 1, 
    "2.4": 1, 
    "1.2": 1, 
    "0.4": 1, 
    "6.8": 1, 
    "7.2": 1, 
    "8.0": 1, 
    "7.6": 1, 
    "3.6": 1, 
    "6.4": 1, 
    "5.2": 1, 
    "2.8": 1, 
    "5.6": 1, 
    "4.4": 1
   }, 
   "species": "fv", 
   "plaza_name": "FV3G10850", 
   "anchor": 0
  }, 
  {
   "id": "16037677", 
   "clusters": {
    "0": 1, 
    "4.8": 3, 
    "2.0": 3, 
    "6.0": 3, 
    "4.0": 3, 
    "0.8": 1, 
    "1.6": 3, 
    "3.2": 3, 
    "2.4": 3, 
    "1.2": 1, 
    "0.4": 1, 
    "6.8": 3, 
    "7.2": 3, 
    "8.0": 3, 
    "7.6": 3, 
    "3.6": 3, 
    "6.4": 3, 
    "5.2": 3, 
    "2.8": 3, 
    "5.6": 3, 
    "4.4": 3
   }, 
   "species": "al", 
   "plaza_name": "AL4G20410", 
   "anchor": 0
  }, 
  {
   "id": "Potri.012G124400", 
   "clusters": {
    "0": 1, 
    "4.8": 1, 
    "2.0": 1, 
    "6.0": 1, 
    "4.0": 1, 
    "0.8": 1, 
    "1.6": 1, 
    "3.2": 1, 
    "2.4": 1, 
    "1.2": 1, 
    "0.4": 1, 
    "6.8": 1, 
    "7.2": 1, 
    "8.0": 1, 
    "7.6": 1, 
    "3.6": 1, 
    "6.4": 1, 
    "5.2": 1, 
    "2.8": 1, 
    "5.6": 1, 
    "4.4": 1
   }, 
   "species": "pt", 
   "plaza_name": "PT12G12440", 
   "anchor": 0
  }, 
  {
   "id": "GRMZM2G410812", 
   "clusters": {
    "0": 0, 
    "4.8": 0, 
    "2.0": 0, 
    "6.0": 0, 
    "4.0": 0, 
    "0.8": 0, 
    "1.6": 0, 
    "3.2": 0, 
    "2.4": 0, 
    "1.2": 0, 
    "0.4": 0, 
    "6.8": 0, 
    "7.2": 0, 
    "8.0": 0, 
    "7.6": 0, 
    "3.6": 0, 
    "6.4": 0, 
    "5.2": 0, 
    "2.8": 0, 
    "5.6": 0, 
    "4.4": 0
   }, 
   "species": "zm", 
   "plaza_name": "ZM06G26500", 
   "anchor": 0
  }, 
  {
   "id": "GRMZM2G180150", 
   "clusters": {
    "0": 0, 
    "4.8": 0, 
    "2.0": 0, 
    "6.0": 0, 
    "4.0": 0, 
    "0.8": 0, 
    "1.6": 0, 
    "3.2": 0, 
    "2.4": 0, 
    "1.2": 0, 
    "0.4": 0, 
    "6.8": 0, 
    "7.2": 0, 
    "8.0": 0, 
    "7.6": 0, 
    "3.6": 0, 
    "6.4": 0, 
    "5.2": 0, 
    "2.8": 0, 
    "5.6": 0, 
    "4.4": 0
   }, 
   "species": "zm", 
   "plaza_name": "ZM10G00450", 
   "anchor": 0
  }, 
  {
   "id": "29840.m000608", 
   "clusters": {
    "0": 1, 
    "4.8": 1, 
    "2.0": 1, 
    "6.0": 1, 
    "4.0": 1, 
    "0.8": 1, 
    "1.6": 1, 
    "3.2": 1, 
    "2.4": 1, 
    "1.2": 1, 
    "0.4": 1, 
    "6.8": 1, 
    "7.2": 1, 
    "8.0": 1, 
    "7.6": 1, 
    "3.6": 1, 
    "6.4": 1, 
    "5.2": 1, 
    "2.8": 1, 
    "5.6": 1, 
    "4.4": 1
   }, 
   "species": "rc", 
   "plaza_name": "RC29840G00050", 
   "anchor": 0
  }, 
  {
   "id": "Potri.015G124000", 
   "clusters": {
    "0": 0, 
    "4.8": 0, 
    "2.0": 0, 
    "6.0": 0, 
    "4.0": 0, 
    "0.8": 0, 
    "1.6": 0, 
    "3.2": 0, 
    "2.4": 0, 
    "1.2": 0, 
    "0.4": 0, 
    "6.8": 0, 
    "7.2": 0, 
    "8.0": 0, 
    "7.6": 0, 
    "3.6": 0, 
    "6.4": 0, 
    "5.2": 0, 
    "2.8": 0, 
    "5.6": 0, 
    "4.4": 0
   }, 
   "species": "pt", 
   "plaza_name": "PT15G12400", 
   "anchor": 0
  }, 
  {
   "id": "GSVIVT01012103001", 
   "clusters": {
    "0": 1, 
    "4.8": 1, 
    "2.0": 1, 
    "6.0": 1, 
    "4.0": 1, 
    "0.8": 1, 
    "1.6": 1, 
    "3.2": 1, 
    "2.4": 1, 
    "1.2": 1, 
    "0.4": 1, 
    "6.8": 1, 
    "7.2": 1, 
    "8.0": 1, 
    "7.6": 1, 
    "3.6": 1, 
    "6.4": 1, 
    "5.2": 1, 
    "2.8": 1, 
    "5.6": 1, 
    "4.4": 1
   }, 
   "species": "vv", 
   "plaza_name": "VV01G09400", 
   "anchor": 0
  }
 ], 
 "tree": "(GRMZM2G447432:0.706055,(Glyma.07G221000:0.00064,(Glyma.20G019300:0.0041,((Medtr4g081610:0.26815,Medtr4g084140:0.00534)0.997:0.0355,((mrna20021:0.04777,(MDP0000443324:0.01576,(MDP0000128017:0.17723,((MDP0000119653:0.00609,MDP0000462973:0.00989)0.986:0.04094,MDP0000003818:0.01409)0.049:0.00086)0.435:0.0086)1:0.03298)0.998:0.02487,((GSVIVT01012103001:0.07473,(Solyc02g068720.2:0.12319,((GRMZM2G180150:0.07715,(LOC_Os08g43130:0.03373,((GRMZM2G089565:0.46036,GRMZM2G410812:0.20512)0.998:0.23933,GRMZM5G886363:0.00055)1:0.11597)0.714:0.01765)1:0.19861,(scaffold00062.200:0.19743,(Phpat.011G004300:0.05799,Phpat.001G023700:0.07864)1:0.61447)0.984:0.07244)1:0.0636)0.973:0.02321)0.972:0.01576,(((Thecc1EG006054:0.02427,Potri.015G123000:0.30783)0.241:0.00084,Gorai.002G164100:0.03566)1:0.03315,((((Medtr3g014450:0.58595,29840.m000608:0.01445)0.865:0.02913,(Potri.012G124400:0.02194,((Potri.015G123500:0.09821,Potri.015G124000:0.08557)0.906:0.09146,(Potri.015G124200:0.08605,(Potri.015G123900:0.00813,Potri.015G124500:0.00911)0.708:0.00517)0.584:0.01432)0.885:0.01872)0.918:0.01309)0.841:0.01247,52317.m000020:0.0621)0.981:0.01576,(evm.TU.supercontig_30.140:0.07436,(Brara.E00925:0.02632,(16037677:0.00893,AT2G35110:0.01019)0.925:0.00745)1:0.13226)0.987:0.02039)0.933:0.00979)0.967:0.01603)0.985:0.01876)1:0.08326)0.991:0.02042)0.472:0.03)1:0.706055);", 
 "links": [
  {
   "distance": 0.9825799999999998, 
   "target": "Phpat.001G023700", 
   "source": "Potri.015G124500"
  }, 
  {
   "distance": 0.6754899999999999, 
   "target": "Medtr3g014450", 
   "source": "Potri.015G124500"
  }, 
  {
   "distance": 0.13498, 
   "target": "52317.m000020", 
   "source": "Potri.015G124500"
  }, 
  {
   "distance": 0.25136, 
   "target": "MDP0000462973", 
   "source": "Potri.015G124500"
  }, 
  {
   "distance": 0.25893, 
   "target": "AT2G35110", 
   "source": "Potri.015G124500"
  }, 
  {
   "distance": 1.67901, 
   "target": "GRMZM2G447432", 
   "source": "Potri.015G124500"
  }, 
  {
   "distance": 0.25732, 
   "target": "Medtr4g084140", 
   "source": "Potri.015G124500"
  }, 
  {
   "distance": 0.26754, 
   "target": "Glyma.07G221000", 
   "source": "Potri.015G124500"
  }, 
  {
   "distance": 0.46702000000000005, 
   "target": "LOC_Os08g43130", 
   "source": "Potri.015G124500"
  }, 
  {
   "distance": 0.21461999999999998, 
   "target": "MDP0000003818", 
   "source": "Potri.015G124500"
  }, 
  {
   "distance": 0.9619299999999997, 
   "target": "Phpat.011G004300", 
   "source": "Potri.015G124500"
  }, 
  {
   "distance": 0.27662000000000003, 
   "target": "Solyc02g068720.2", 
   "source": "Potri.015G124500"
  }, 
  {
   "distance": 0.3769, 
   "target": "MDP0000128017", 
   "source": "Potri.015G124500"
  }, 
  {
   "distance": 0.4869, 
   "target": "scaffold00062.200", 
   "source": "Potri.015G124500"
  }, 
  {
   "distance": 0.20682999999999999, 
   "target": "MDP0000443324", 
   "source": "Potri.015G124500"
  }, 
  {
   "distance": 1.24895, 
   "target": "GRMZM2G089565", 
   "source": "Potri.015G124500"
  }, 
  {
   "distance": 0.21827000000000002, 
   "target": "Potri.015G123500", 
   "source": "Potri.015G124500"
  }, 
  {
   "distance": 0.24756, 
   "target": "MDP0000119653", 
   "source": "Potri.015G124500"
  }, 
  {
   "distance": 0.44025000000000003, 
   "target": "Potri.015G123000", 
   "source": "Potri.015G124500"
  }, 
  {
   "distance": 0.15669, 
   "target": "Thecc1EG006054", 
   "source": "Potri.015G124500"
  }, 
  {
   "distance": 0.10032999999999999, 
   "target": "Potri.015G124200", 
   "source": "Potri.015G124500"
  }, 
  {
   "distance": 0.26761, 
   "target": "Brara.E00925", 
   "source": "Potri.015G124500"
  }, 
  {
   "distance": 0.01724, 
   "target": "Potri.015G123900", 
   "source": "Potri.015G124500"
  }, 
  {
   "distance": 0.18338999999999997, 
   "target": "evm.TU.supercontig_30.140", 
   "source": "Potri.015G124500"
  }, 
  {
   "distance": 0.10399, 
   "target": "29840.m000608", 
   "source": "Potri.015G124500"
  }, 
  {
   "distance": 0.52013, 
   "target": "Medtr4g081610", 
   "source": "Potri.015G124500"
  }, 
  {
   "distance": 0.54981, 
   "target": "GRMZM5G886363", 
   "source": "Potri.015G124500"
  }, 
  {
   "distance": 0.241, 
   "target": "Glyma.20G019300", 
   "source": "Potri.015G124500"
  }, 
  {
   "distance": 0.20585999999999996, 
   "target": "mrna20021", 
   "source": "Potri.015G124500"
  }, 
  {
   "distance": 0.25767, 
   "target": "16037677", 
   "source": "Potri.015G124500"
  }, 
  {
   "distance": 0.06926, 
   "target": "Potri.012G124400", 
   "source": "Potri.015G124500"
  }, 
  {
   "distance": 0.9937099999999999, 
   "target": "GRMZM2G410812", 
   "source": "Potri.015G124500"
  }, 
  {
   "distance": 0.49279, 
   "target": "GRMZM2G180150", 
   "source": "Potri.015G124500"
  }, 
  {
   "distance": 0.16723999999999997, 
   "target": "Gorai.002G164100", 
   "source": "Potri.015G124500"
  }, 
  {
   "distance": 0.20563, 
   "target": "Potri.015G124000", 
   "source": "Potri.015G124500"
  }, 
  {
   "distance": 0.20494999999999997, 
   "target": "GSVIVT01012103001", 
   "source": "Potri.015G124500"
  }, 
  {
   "distance": 1.5372499999999998, 
   "target": "Medtr3g014450", 
   "source": "Phpat.001G023700"
  }, 
  {
   "distance": 0.9717999999999999, 
   "target": "52317.m000020", 
   "source": "Phpat.001G023700"
  }, 
  {
   "distance": 1.00502, 
   "target": "MDP0000462973", 
   "source": "Phpat.001G023700"
  }, 
  {
   "distance": 1.0642299999999998, 
   "target": "AT2G35110", 
   "source": "Phpat.001G023700"
  }, 
  {
   "distance": 2.4326700000000003, 
   "target": "GRMZM2G447432", 
   "source": "Phpat.001G023700"
  }, 
  {
   "distance": 1.01098, 
   "target": "Medtr4g084140", 
   "source": "Phpat.001G023700"
  }, 
  {
   "distance": 1.0211999999999999, 
   "target": "Glyma.07G221000", 
   "source": "Phpat.001G023700"
  }, 
  {
   "distance": 1.01554, 
   "target": "LOC_Os08g43130", 
   "source": "Phpat.001G023700"
  }, 
  {
   "distance": 0.96828, 
   "target": "MDP0000003818", 
   "source": "Phpat.001G023700"
  }, 
  {
   "distance": 0.13663, 
   "target": "Phpat.011G004300", 
   "source": "Phpat.001G023700"
  }, 
  {
   "distance": 0.9523400000000001, 
   "target": "Solyc02g068720.2", 
   "source": "Phpat.001G023700"
  }, 
  {
   "distance": 1.13056, 
   "target": "MDP0000128017", 
   "source": "Phpat.001G023700"
  }, 
  {
   "distance": 0.8905399999999999, 
   "target": "scaffold00062.200", 
   "source": "Phpat.001G023700"
  }, 
  {
   "distance": 0.9604899999999998, 
   "target": "MDP0000443324", 
   "source": "Phpat.001G023700"
  }, 
  {
   "distance": 1.79747, 
   "target": "GRMZM2G089565", 
   "source": "Phpat.001G023700"
  }, 
  {
   "distance": 1.14365, 
   "target": "Potri.015G123500", 
   "source": "Phpat.001G023700"
  }, 
  {
   "distance": 1.00122, 
   "target": "MDP0000119653", 
   "source": "Phpat.001G023700"
  }, 
  {
   "distance": 1.2259699999999998, 
   "target": "Potri.015G123000", 
   "source": "Phpat.001G023700"
  }, 
  {
   "distance": 0.9424099999999999, 
   "target": "Thecc1EG006054", 
   "source": "Phpat.001G023700"
  }, 
  {
   "distance": 1.0543499999999997, 
   "target": "Potri.015G124200", 
   "source": "Phpat.001G023700"
  }, 
  {
   "distance": 1.0729099999999998, 
   "target": "Brara.E00925", 
   "source": "Phpat.001G023700"
  }, 
  {
   "distance": 0.9815999999999998, 
   "target": "Potri.015G123900", 
   "source": "Phpat.001G023700"
  }, 
  {
   "distance": 0.9886899999999998, 
   "target": "evm.TU.supercontig_30.140", 
   "source": "Phpat.001G023700"
  }, 
  {
   "distance": 0.9657499999999998, 
   "target": "29840.m000608", 
   "source": "Phpat.001G023700"
  }, 
  {
   "distance": 1.27379, 
   "target": "Medtr4g081610", 
   "source": "Phpat.001G023700"
  }, 
  {
   "distance": 1.09833, 
   "target": "GRMZM5G886363", 
   "source": "Phpat.001G023700"
  }, 
  {
   "distance": 0.9946599999999999, 
   "target": "Glyma.20G019300", 
   "source": "Phpat.001G023700"
  }, 
  {
   "distance": 0.9595199999999999, 
   "target": "mrna20021", 
   "source": "Phpat.001G023700"
  }, 
  {
   "distance": 1.0629699999999997, 
   "target": "16037677", 
   "source": "Phpat.001G023700"
  }, 
  {
   "distance": 0.9571999999999998, 
   "target": "Potri.012G124400", 
   "source": "Phpat.001G023700"
  }, 
  {
   "distance": 1.5422300000000002, 
   "target": "GRMZM2G410812", 
   "source": "Phpat.001G023700"
  }, 
  {
   "distance": 1.04131, 
   "target": "GRMZM2G180150", 
   "source": "Phpat.001G023700"
  }, 
  {
   "distance": 0.9529599999999999, 
   "target": "Gorai.002G164100", 
   "source": "Phpat.001G023700"
  }, 
  {
   "distance": 1.13101, 
   "target": "Potri.015G124000", 
   "source": "Phpat.001G023700"
  }, 
  {
   "distance": 0.9270899999999999, 
   "target": "GSVIVT01012103001", 
   "source": "Phpat.001G023700"
  }, 
  {
   "distance": 0.68965, 
   "target": "52317.m000020", 
   "source": "Medtr3g014450"
  }, 
  {
   "distance": 0.8060299999999999, 
   "target": "MDP0000462973", 
   "source": "Medtr3g014450"
  }, 
  {
   "distance": 0.8136, 
   "target": "AT2G35110", 
   "source": "Medtr3g014450"
  }, 
  {
   "distance": 2.23368, 
   "target": "GRMZM2G447432", 
   "source": "Medtr3g014450"
  }, 
  {
   "distance": 0.8119899999999999, 
   "target": "Medtr4g084140", 
   "source": "Medtr3g014450"
  }, 
  {
   "distance": 0.8222099999999999, 
   "target": "Glyma.07G221000", 
   "source": "Medtr3g014450"
  }, 
  {
   "distance": 1.02169, 
   "target": "LOC_Os08g43130", 
   "source": "Medtr3g014450"
  }, 
  {
   "distance": 0.7692899999999999, 
   "target": "MDP0000003818", 
   "source": "Medtr3g014450"
  }, 
  {
   "distance": 1.5166, 
   "target": "Phpat.011G004300", 
   "source": "Medtr3g014450"
  }, 
  {
   "distance": 0.8312899999999999, 
   "target": "Solyc02g068720.2", 
   "source": "Medtr3g014450"
  }, 
  {
   "distance": 0.9315699999999999, 
   "target": "MDP0000128017", 
   "source": "Medtr3g014450"
  }, 
  {
   "distance": 1.0415699999999999, 
   "target": "scaffold00062.200", 
   "source": "Medtr3g014450"
  }, 
  {
   "distance": 0.7614999999999998, 
   "target": "MDP0000443324", 
   "source": "Medtr3g014450"
  }, 
  {
   "distance": 1.80362, 
   "target": "GRMZM2G089565", 
   "source": "Medtr3g014450"
  }, 
  {
   "distance": 0.83656, 
   "target": "Potri.015G123500", 
   "source": "Medtr3g014450"
  }, 
  {
   "distance": 0.8022299999999999, 
   "target": "MDP0000119653", 
   "source": "Medtr3g014450"
  }, 
  {
   "distance": 0.9949199999999999, 
   "target": "Potri.015G123000", 
   "source": "Medtr3g014450"
  }, 
  {
   "distance": 0.7113599999999999, 
   "target": "Thecc1EG006054", 
   "source": "Medtr3g014450"
  }, 
  {
   "distance": 0.7472599999999999, 
   "target": "Potri.015G124200", 
   "source": "Medtr3g014450"
  }, 
  {
   "distance": 0.82228, 
   "target": "Brara.E00925", 
   "source": "Medtr3g014450"
  }, 
  {
   "distance": 0.6745099999999999, 
   "target": "Potri.015G123900", 
   "source": "Medtr3g014450"
  }, 
  {
   "distance": 0.7380599999999999, 
   "target": "evm.TU.supercontig_30.140", 
   "source": "Medtr3g014450"
  }, 
  {
   "distance": 0.6003999999999999, 
   "target": "29840.m000608", 
   "source": "Medtr3g014450"
  }, 
  {
   "distance": 1.0747999999999998, 
   "target": "Medtr4g081610", 
   "source": "Medtr3g014450"
  }, 
  {
   "distance": 1.1044800000000001, 
   "target": "GRMZM5G886363", 
   "source": "Medtr3g014450"
  }, 
  {
   "distance": 0.7956699999999999, 
   "target": "Glyma.20G019300", 
   "source": "Medtr3g014450"
  }, 
  {
   "distance": 0.7605299999999999, 
   "target": "mrna20021", 
   "source": "Medtr3g014450"
  }, 
  {
   "distance": 0.81234, 
   "target": "16037677", 
   "source": "Medtr3g014450"
  }, 
  {
   "distance": 0.65011, 
   "target": "Potri.012G124400", 
   "source": "Medtr3g014450"
  }, 
  {
   "distance": 1.5483799999999999, 
   "target": "GRMZM2G410812", 
   "source": "Medtr3g014450"
  }, 
  {
   "distance": 1.04746, 
   "target": "GRMZM2G180150", 
   "source": "Medtr3g014450"
  }, 
  {
   "distance": 0.7219099999999999, 
   "target": "Gorai.002G164100", 
   "source": "Medtr3g014450"
  }, 
  {
   "distance": 0.82392, 
   "target": "Potri.015G124000", 
   "source": "Medtr3g014450"
  }, 
  {
   "distance": 0.7596199999999999, 
   "target": "GSVIVT01012103001", 
   "source": "Medtr3g014450"
  }, 
  {
   "distance": 0.24058, 
   "target": "MDP0000462973", 
   "source": "52317.m000020"
  }, 
  {
   "distance": 0.24814999999999998, 
   "target": "AT2G35110", 
   "source": "52317.m000020"
  }, 
  {
   "distance": 1.6682299999999999, 
   "target": "GRMZM2G447432", 
   "source": "52317.m000020"
  }, 
  {
   "distance": 0.24653999999999998, 
   "target": "Medtr4g084140", 
   "source": "52317.m000020"
  }, 
  {
   "distance": 0.25676, 
   "target": "Glyma.07G221000", 
   "source": "52317.m000020"
  }, 
  {
   "distance": 0.45624000000000003, 
   "target": "LOC_Os08g43130", 
   "source": "52317.m000020"
  }, 
  {
   "distance": 0.20384, 
   "target": "MDP0000003818", 
   "source": "52317.m000020"
  }, 
  {
   "distance": 0.9511499999999998, 
   "target": "Phpat.011G004300", 
   "source": "52317.m000020"
  }, 
  {
   "distance": 0.26584, 
   "target": "Solyc02g068720.2", 
   "source": "52317.m000020"
  }, 
  {
   "distance": 0.36612, 
   "target": "MDP0000128017", 
   "source": "52317.m000020"
  }, 
  {
   "distance": 0.47612, 
   "target": "scaffold00062.200", 
   "source": "52317.m000020"
  }, 
  {
   "distance": 0.19604999999999997, 
   "target": "MDP0000443324", 
   "source": "52317.m000020"
  }, 
  {
   "distance": 1.23817, 
   "target": "GRMZM2G089565", 
   "source": "52317.m000020"
  }, 
  {
   "distance": 0.29605000000000004, 
   "target": "Potri.015G123500", 
   "source": "52317.m000020"
  }, 
  {
   "distance": 0.23677999999999996, 
   "target": "MDP0000119653", 
   "source": "52317.m000020"
  }, 
  {
   "distance": 0.42947, 
   "target": "Potri.015G123000", 
   "source": "52317.m000020"
  }, 
  {
   "distance": 0.14590999999999998, 
   "target": "Thecc1EG006054", 
   "source": "52317.m000020"
  }, 
  {
   "distance": 0.20675, 
   "target": "Potri.015G124200", 
   "source": "52317.m000020"
  }, 
  {
   "distance": 0.25683, 
   "target": "Brara.E00925", 
   "source": "52317.m000020"
  }, 
  {
   "distance": 0.134, 
   "target": "Potri.015G123900", 
   "source": "52317.m000020"
  }, 
  {
   "distance": 0.17260999999999999, 
   "target": "evm.TU.supercontig_30.140", 
   "source": "52317.m000020"
  }, 
  {
   "distance": 0.11815, 
   "target": "29840.m000608", 
   "source": "52317.m000020"
  }, 
  {
   "distance": 0.50935, 
   "target": "Medtr4g081610", 
   "source": "52317.m000020"
  }, 
  {
   "distance": 0.53903, 
   "target": "GRMZM5G886363", 
   "source": "52317.m000020"
  }, 
  {
   "distance": 0.23021999999999998, 
   "target": "Glyma.20G019300", 
   "source": "52317.m000020"
  }, 
  {
   "distance": 0.19507999999999998, 
   "target": "mrna20021", 
   "source": "52317.m000020"
  }, 
  {
   "distance": 0.24688999999999997, 
   "target": "16037677", 
   "source": "52317.m000020"
  }, 
  {
   "distance": 0.1096, 
   "target": "Potri.012G124400", 
   "source": "52317.m000020"
  }, 
  {
   "distance": 0.98293, 
   "target": "GRMZM2G410812", 
   "source": "52317.m000020"
  }, 
  {
   "distance": 0.48201, 
   "target": "GRMZM2G180150", 
   "source": "52317.m000020"
  }, 
  {
   "distance": 0.15646, 
   "target": "Gorai.002G164100", 
   "source": "52317.m000020"
  }, 
  {
   "distance": 0.28341, 
   "target": "Potri.015G124000", 
   "source": "52317.m000020"
  }, 
  {
   "distance": 0.19416999999999998, 
   "target": "GSVIVT01012103001", 
   "source": "52317.m000020"
  }, 
  {
   "distance": 0.33301000000000003, 
   "target": "AT2G35110", 
   "source": "MDP0000462973"
  }, 
  {
   "distance": 1.66393, 
   "target": "GRMZM2G447432", 
   "source": "MDP0000462973"
  }, 
  {
   "distance": 0.24224, 
   "target": "Medtr4g084140", 
   "source": "MDP0000462973"
  }, 
  {
   "distance": 0.25246, 
   "target": "Glyma.07G221000", 
   "source": "MDP0000462973"
  }, 
  {
   "distance": 0.48946, 
   "target": "LOC_Os08g43130", 
   "source": "MDP0000462973"
  }, 
  {
   "distance": 0.06492, 
   "target": "MDP0000003818", 
   "source": "MDP0000462973"
  }, 
  {
   "distance": 0.98437, 
   "target": "Phpat.011G004300", 
   "source": "MDP0000462973"
  }, 
  {
   "distance": 0.29906, 
   "target": "Solyc02g068720.2", 
   "source": "MDP0000462973"
  }, 
  {
   "distance": 0.22892, 
   "target": "MDP0000128017", 
   "source": "MDP0000462973"
  }, 
  {
   "distance": 0.50934, 
   "target": "scaffold00062.200", 
   "source": "MDP0000462973"
  }, 
  {
   "distance": 0.07604999999999999, 
   "target": "MDP0000443324", 
   "source": "MDP0000462973"
  }, 
  {
   "distance": 1.2713900000000002, 
   "target": "GRMZM2G089565", 
   "source": "MDP0000462973"
  }, 
  {
   "distance": 0.41242999999999996, 
   "target": "Potri.015G123500", 
   "source": "MDP0000462973"
  }, 
  {
   "distance": 0.01598, 
   "target": "MDP0000119653", 
   "source": "MDP0000462973"
  }, 
  {
   "distance": 0.49474999999999997, 
   "target": "Potri.015G123000", 
   "source": "MDP0000462973"
  }, 
  {
   "distance": 0.21119, 
   "target": "Thecc1EG006054", 
   "source": "MDP0000462973"
  }, 
  {
   "distance": 0.32313, 
   "target": "Potri.015G124200", 
   "source": "MDP0000462973"
  }, 
  {
   "distance": 0.34169, 
   "target": "Brara.E00925", 
   "source": "MDP0000462973"
  }, 
  {
   "distance": 0.25038, 
   "target": "Potri.015G123900", 
   "source": "MDP0000462973"
  }, 
  {
   "distance": 0.25747, 
   "target": "evm.TU.supercontig_30.140", 
   "source": "MDP0000462973"
  }, 
  {
   "distance": 0.23452999999999996, 
   "target": "29840.m000608", 
   "source": "MDP0000462973"
  }, 
  {
   "distance": 0.50505, 
   "target": "Medtr4g081610", 
   "source": "MDP0000462973"
  }, 
  {
   "distance": 0.5722499999999999, 
   "target": "GRMZM5G886363", 
   "source": "MDP0000462973"
  }, 
  {
   "distance": 0.22591999999999998, 
   "target": "Glyma.20G019300", 
   "source": "MDP0000462973"
  }, 
  {
   "distance": 0.14104, 
   "target": "mrna20021", 
   "source": "MDP0000462973"
  }, 
  {
   "distance": 0.33175000000000004, 
   "target": "16037677", 
   "source": "MDP0000462973"
  }, 
  {
   "distance": 0.22597999999999996, 
   "target": "Potri.012G124400", 
   "source": "MDP0000462973"
  }, 
  {
   "distance": 1.0161499999999999, 
   "target": "GRMZM2G410812", 
   "source": "MDP0000462973"
  }, 
  {
   "distance": 0.5152300000000001, 
   "target": "GRMZM2G180150", 
   "source": "MDP0000462973"
  }, 
  {
   "distance": 0.22174, 
   "target": "Gorai.002G164100", 
   "source": "MDP0000462973"
  }, 
  {
   "distance": 0.39979, 
   "target": "Potri.015G124000", 
   "source": "MDP0000462973"
  }, 
  {
   "distance": 0.22738999999999998, 
   "target": "GSVIVT01012103001", 
   "source": "MDP0000462973"
  }, 
  {
   "distance": 1.7606600000000001, 
   "target": "GRMZM2G447432", 
   "source": "AT2G35110"
  }, 
  {
   "distance": 0.33896999999999994, 
   "target": "Medtr4g084140", 
   "source": "AT2G35110"
  }, 
  {
   "distance": 0.34919, 
   "target": "Glyma.07G221000", 
   "source": "AT2G35110"
  }, 
  {
   "distance": 0.54867, 
   "target": "LOC_Os08g43130", 
   "source": "AT2G35110"
  }, 
  {
   "distance": 0.29627000000000003, 
   "target": "MDP0000003818", 
   "source": "AT2G35110"
  }, 
  {
   "distance": 1.0435799999999997, 
   "target": "Phpat.011G004300", 
   "source": "AT2G35110"
  }, 
  {
   "distance": 0.35827000000000003, 
   "ka": "0.1484", 
   "target": "Solyc02g068720.2", 
   "evalue": "0.0", 
   "block_score": "305.0", 
   "ks": "2.7832", 
   "source": "AT2G35110"
  }, 
  {
   "distance": 0.45855, 
   "target": "MDP0000128017", 
   "source": "AT2G35110"
  }, 
  {
   "distance": 0.56855, 
   "target": "scaffold00062.200", 
   "source": "AT2G35110"
  }, 
  {
   "distance": 0.28847999999999996, 
   "target": "MDP0000443324", 
   "source": "AT2G35110"
  }, 
  {
   "distance": 1.3305999999999998, 
   "target": "GRMZM2G089565", 
   "source": "AT2G35110"
  }, 
  {
   "distance": 0.42000000000000004, 
   "target": "Potri.015G123500", 
   "source": "AT2G35110"
  }, 
  {
   "distance": 0.32921000000000006, 
   "target": "MDP0000119653", 
   "source": "AT2G35110"
  }, 
  {
   "distance": 0.5218999999999999, 
   "target": "Potri.015G123000", 
   "source": "AT2G35110"
  }, 
  {
   "distance": 0.23833999999999997, 
   "ka": "0.1027", 
   "target": "Thecc1EG006054", 
   "evalue": "0.0", 
   "block_score": "405.0", 
   "ks": "1.3964", 
   "source": "AT2G35110"
  }, 
  {
   "distance": 0.3307, 
   "target": "Potri.015G124200", 
   "source": "AT2G35110"
  }, 
  {
   "distance": 0.04396, 
   "ka": "0.0232", 
   "target": "Brara.E00925", 
   "evalue": "0.0", 
   "block_score": "15208.0", 
   "ks": "0.3331", 
   "source": "AT2G35110"
  }, 
  {
   "distance": 0.25795, 
   "target": "Potri.015G123900", 
   "source": "AT2G35110"
  }, 
  {
   "distance": 0.22426, 
   "target": "evm.TU.supercontig_30.140", 
   "source": "AT2G35110"
  }, 
  {
   "distance": 0.24209999999999998, 
   "target": "29840.m000608", 
   "source": "AT2G35110"
  }, 
  {
   "distance": 0.60178, 
   "target": "Medtr4g081610", 
   "source": "AT2G35110"
  }, 
  {
   "distance": 0.63146, 
   "target": "GRMZM5G886363", 
   "source": "AT2G35110"
  }, 
  {
   "distance": 0.32265, 
   "target": "Glyma.20G019300", 
   "source": "AT2G35110"
  }, 
  {
   "distance": 0.28751, 
   "ka": "0.1176", 
   "target": "mrna20021", 
   "evalue": "0.0", 
   "block_score": "338.0", 
   "ks": "1.7708", 
   "source": "AT2G35110"
  }, 
  {
   "distance": 0.019119999999999998, 
   "ka": "0.0096", 
   "target": "16037677", 
   "evalue": "0.0", 
   "block_score": "54203.0", 
   "ks": "0.1031", 
   "source": "AT2G35110"
  }, 
  {
   "distance": 0.23354999999999998, 
   "target": "Potri.012G124400", 
   "source": "AT2G35110"
  }, 
  {
   "distance": 1.0753599999999999, 
   "target": "GRMZM2G410812", 
   "source": "AT2G35110"
  }, 
  {
   "distance": 0.57444, 
   "target": "GRMZM2G180150", 
   "source": "AT2G35110"
  }, 
  {
   "distance": 0.24888999999999997, 
   "target": "Gorai.002G164100", 
   "source": "AT2G35110"
  }, 
  {
   "distance": 0.40736, 
   "target": "Potri.015G124000", 
   "source": "AT2G35110"
  }, 
  {
   "distance": 0.2866, 
   "ka": "0.1247", 
   "target": "GSVIVT01012103001", 
   "evalue": "0.0", 
   "block_score": "358.0", 
   "ks": "1.4163", 
   "source": "AT2G35110"
  }, 
  {
   "distance": 1.5033699999999999, 
   "target": "Medtr4g084140", 
   "source": "GRMZM2G447432"
  }, 
  {
   "distance": 1.41275, 
   "target": "Glyma.07G221000", 
   "source": "GRMZM2G447432"
  }, 
  {
   "distance": 1.91711, 
   "target": "LOC_Os08g43130", 
   "source": "GRMZM2G447432"
  }, 
  {
   "distance": 1.6271900000000001, 
   "target": "MDP0000003818", 
   "source": "GRMZM2G447432"
  }, 
  {
   "distance": 2.41202, 
   "target": "Phpat.011G004300", 
   "source": "GRMZM2G447432"
  }, 
  {
   "distance": 1.7267099999999997, 
   "target": "Solyc02g068720.2", 
   "source": "GRMZM2G447432"
  }, 
  {
   "distance": 1.7894700000000001, 
   "target": "MDP0000128017", 
   "source": "GRMZM2G447432"
  }, 
  {
   "distance": 1.9369900000000002, 
   "target": "scaffold00062.200", 
   "source": "GRMZM2G447432"
  }, 
  {
   "distance": 1.6194, 
   "target": "MDP0000443324", 
   "source": "GRMZM2G447432"
  }, 
  {
   "distance": 2.69904, 
   "target": "GRMZM2G089565", 
   "source": "GRMZM2G447432"
  }, 
  {
   "distance": 1.84008, 
   "target": "Potri.015G123500", 
   "source": "GRMZM2G447432"
  }, 
  {
   "distance": 1.66013, 
   "target": "MDP0000119653", 
   "source": "GRMZM2G447432"
  }, 
  {
   "distance": 1.9224, 
   "target": "Potri.015G123000", 
   "source": "GRMZM2G447432"
  }, 
  {
   "distance": 1.63884, 
   "target": "Thecc1EG006054", 
   "source": "GRMZM2G447432"
  }, 
  {
   "distance": 1.7507799999999998, 
   "target": "Potri.015G124200", 
   "source": "GRMZM2G447432"
  }, 
  {
   "distance": 1.7693400000000001, 
   "target": "Brara.E00925", 
   "source": "GRMZM2G447432"
  }, 
  {
   "distance": 1.67803, 
   "target": "Potri.015G123900", 
   "source": "GRMZM2G447432"
  }, 
  {
   "distance": 1.68512, 
   "target": "evm.TU.supercontig_30.140", 
   "source": "GRMZM2G447432"
  }, 
  {
   "distance": 1.6621799999999998, 
   "target": "29840.m000608", 
   "source": "GRMZM2G447432"
  }, 
  {
   "distance": 1.7661800000000003, 
   "target": "Medtr4g081610", 
   "source": "GRMZM2G447432"
  }, 
  {
   "distance": 1.9999000000000002, 
   "target": "GRMZM5G886363", 
   "source": "GRMZM2G447432"
  }, 
  {
   "distance": 1.44621, 
   "target": "Glyma.20G019300", 
   "source": "GRMZM2G447432"
  }, 
  {
   "distance": 1.61843, 
   "target": "mrna20021", 
   "source": "GRMZM2G447432"
  }, 
  {
   "distance": 1.7593999999999999, 
   "target": "16037677", 
   "source": "GRMZM2G447432"
  }, 
  {
   "distance": 1.65363, 
   "target": "Potri.012G124400", 
   "source": "GRMZM2G447432"
  }, 
  {
   "distance": 2.4438, 
   "target": "GRMZM2G410812", 
   "source": "GRMZM2G447432"
  }, 
  {
   "distance": 1.9428800000000002, 
   "target": "GRMZM2G180150", 
   "source": "GRMZM2G447432"
  }, 
  {
   "distance": 1.64939, 
   "target": "Gorai.002G164100", 
   "source": "GRMZM2G447432"
  }, 
  {
   "distance": 1.8274400000000002, 
   "target": "Potri.015G124000", 
   "source": "GRMZM2G447432"
  }, 
  {
   "distance": 1.65504, 
   "target": "GSVIVT01012103001", 
   "source": "GRMZM2G447432"
  }, 
  {
   "distance": 0.0919, 
   "ka": "0.0736", 
   "target": "Glyma.07G221000", 
   "evalue": "0.0", 
   "block_score": "9964.0", 
   "ks": "0.4081", 
   "source": "Medtr4g084140"
  }, 
  {
   "distance": 0.49542, 
   "target": "LOC_Os08g43130", 
   "source": "Medtr4g084140"
  }, 
  {
   "distance": 0.2055, 
   "target": "MDP0000003818", 
   "source": "Medtr4g084140"
  }, 
  {
   "distance": 0.9903299999999998, 
   "target": "Phpat.011G004300", 
   "source": "Medtr4g084140"
  }, 
  {
   "distance": 0.30501999999999996, 
   "ka": "0.14", 
   "target": "Solyc02g068720.2", 
   "evalue": "0.0", 
   "block_score": "578.0", 
   "ks": "1.7659", 
   "source": "Medtr4g084140"
  }, 
  {
   "distance": 0.36778, 
   "target": "MDP0000128017", 
   "source": "Medtr4g084140"
  }, 
  {
   "distance": 0.5153, 
   "target": "scaffold00062.200", 
   "source": "Medtr4g084140"
  }, 
  {
   "distance": 0.19771, 
   "target": "MDP0000443324", 
   "source": "Medtr4g084140"
  }, 
  {
   "distance": 1.2773500000000002, 
   "target": "GRMZM2G089565", 
   "source": "Medtr4g084140"
  }, 
  {
   "distance": 0.41839, 
   "target": "Potri.015G123500", 
   "source": "Medtr4g084140"
  }, 
  {
   "distance": 0.23843999999999999, 
   "target": "MDP0000119653", 
   "source": "Medtr4g084140"
  }, 
  {
   "distance": 0.50071, 
   "ka": "0.2574", 
   "target": "Potri.015G123000", 
   "evalue": "1e-23", 
   "block_score": "488.0", 
   "ks": "2.0966", 
   "source": "Medtr4g084140"
  }, 
  {
   "distance": 0.21715, 
   "target": "Thecc1EG006054", 
   "source": "Medtr4g084140"
  }, 
  {
   "distance": 0.32909, 
   "target": "Potri.015G124200", 
   "source": "Medtr4g084140"
  }, 
  {
   "distance": 0.34764999999999996, 
   "ka": "0.1424", 
   "target": "Brara.E00925", 
   "evalue": "0.0", 
   "block_score": "216.0", 
   "ks": "2.108", 
   "source": "Medtr4g084140"
  }, 
  {
   "distance": 0.25634, 
   "target": "Potri.015G123900", 
   "source": "Medtr4g084140"
  }, 
  {
   "distance": 0.26342999999999994, 
   "target": "evm.TU.supercontig_30.140", 
   "source": "Medtr4g084140"
  }, 
  {
   "distance": 0.24048999999999998, 
   "target": "29840.m000608", 
   "source": "Medtr4g084140"
  }, 
  {
   "distance": 0.27349, 
   "target": "Medtr4g081610", 
   "source": "Medtr4g084140"
  }, 
  {
   "distance": 0.57821, 
   "target": "GRMZM5G886363", 
   "source": "Medtr4g084140"
  }, 
  {
   "distance": 0.06536, 
   "ka": "0.0325", 
   "target": "Glyma.20G019300", 
   "evalue": "0.0", 
   "block_score": "3559.0", 
   "ks": "0.3772", 
   "source": "Medtr4g084140"
  }, 
  {
   "distance": 0.19674, 
   "ka": "0.0957", 
   "target": "mrna20021", 
   "evalue": "0.0", 
   "block_score": "704.0", 
   "ks": "1.1185", 
   "source": "Medtr4g084140"
  }, 
  {
   "distance": 0.33770999999999995, 
   "target": "16037677", 
   "source": "Medtr4g084140"
  }, 
  {
   "distance": 0.23193999999999998, 
   "ka": "0.1021", 
   "target": "Potri.012G124400", 
   "evalue": "0.0", 
   "block_score": "374.0", 
   "ks": "1.4054", 
   "source": "Medtr4g084140"
  }, 
  {
   "distance": 1.02211, 
   "target": "GRMZM2G410812", 
   "source": "Medtr4g084140"
  }, 
  {
   "distance": 0.52119, 
   "target": "GRMZM2G180150", 
   "source": "Medtr4g084140"
  }, 
  {
   "distance": 0.22769999999999999, 
   "target": "Gorai.002G164100", 
   "source": "Medtr4g084140"
  }, 
  {
   "distance": 0.40575, 
   "target": "Potri.015G124000", 
   "source": "Medtr4g084140"
  }, 
  {
   "distance": 0.23335, 
   "target": "GSVIVT01012103001", 
   "source": "Medtr4g084140"
  }, 
  {
   "distance": 0.50564, 
   "target": "LOC_Os08g43130", 
   "source": "Glyma.07G221000"
  }, 
  {
   "distance": 0.21572, 
   "target": "MDP0000003818", 
   "source": "Glyma.07G221000"
  }, 
  {
   "distance": 1.0005499999999998, 
   "target": "Phpat.011G004300", 
   "source": "Glyma.07G221000"
  }, 
  {
   "distance": 0.31523999999999996, 
   "ka": "0.2018", 
   "target": "Solyc02g068720.2", 
   "evalue": "0.0", 
   "block_score": "434.0", 
   "ks": "1.3174", 
   "source": "Glyma.07G221000"
  }, 
  {
   "distance": 0.378, 
   "target": "MDP0000128017", 
   "source": "Glyma.07G221000"
  }, 
  {
   "distance": 0.52552, 
   "target": "scaffold00062.200", 
   "source": "Glyma.07G221000"
  }, 
  {
   "distance": 0.20793, 
   "target": "MDP0000443324", 
   "source": "Glyma.07G221000"
  }, 
  {
   "distance": 1.2875700000000003, 
   "target": "GRMZM2G089565", 
   "source": "Glyma.07G221000"
  }, 
  {
   "distance": 0.42861000000000005, 
   "target": "Potri.015G123500", 
   "source": "Glyma.07G221000"
  }, 
  {
   "distance": 0.24866, 
   "target": "MDP0000119653", 
   "source": "Glyma.07G221000"
  }, 
  {
   "distance": 0.51093, 
   "target": "Potri.015G123000", 
   "source": "Glyma.07G221000"
  }, 
  {
   "distance": 0.22737, 
   "target": "Thecc1EG006054", 
   "source": "Glyma.07G221000"
  }, 
  {
   "distance": 0.33931, 
   "target": "Potri.015G124200", 
   "source": "Glyma.07G221000"
  }, 
  {
   "distance": 0.35787, 
   "target": "Brara.E00925", 
   "source": "Glyma.07G221000"
  }, 
  {
   "distance": 0.26656, 
   "ka": "0.1704", 
   "target": "Potri.015G123900", 
   "evalue": "0.0", 
   "block_score": "219.0", 
   "ks": "1.2446", 
   "source": "Glyma.07G221000"
  }, 
  {
   "distance": 0.27364999999999995, 
   "target": "evm.TU.supercontig_30.140", 
   "source": "Glyma.07G221000"
  }, 
  {
   "distance": 0.25071, 
   "target": "29840.m000608", 
   "source": "Glyma.07G221000"
  }, 
  {
   "distance": 0.35470999999999997, 
   "target": "Medtr4g081610", 
   "source": "Glyma.07G221000"
  }, 
  {
   "distance": 0.58843, 
   "target": "GRMZM5G886363", 
   "source": "Glyma.07G221000"
  }, 
  {
   "distance": 0.03474, 
   "ka": "0.0195", 
   "target": "Glyma.20G019300", 
   "evalue": "0.0", 
   "block_score": "4019.0", 
   "ks": "0.1081", 
   "source": "Glyma.07G221000"
  }, 
  {
   "distance": 0.20696, 
   "ka": "0.1315", 
   "target": "mrna20021", 
   "evalue": "0.0", 
   "block_score": "495.0", 
   "ks": "0.9302", 
   "source": "Glyma.07G221000"
  }, 
  {
   "distance": 0.34792999999999996, 
   "target": "16037677", 
   "source": "Glyma.07G221000"
  }, 
  {
   "distance": 0.24216000000000001, 
   "ka": "0.1449", 
   "target": "Potri.012G124400", 
   "evalue": "0.0", 
   "block_score": "206.0", 
   "ks": "1.1645", 
   "source": "Glyma.07G221000"
  }, 
  {
   "distance": 1.03233, 
   "target": "GRMZM2G410812", 
   "source": "Glyma.07G221000"
  }, 
  {
   "distance": 0.53141, 
   "target": "GRMZM2G180150", 
   "source": "Glyma.07G221000"
  }, 
  {
   "distance": 0.23792, 
   "target": "Gorai.002G164100", 
   "source": "Glyma.07G221000"
  }, 
  {
   "distance": 0.41596999999999995, 
   "target": "Potri.015G124000", 
   "source": "Glyma.07G221000"
  }, 
  {
   "distance": 0.24356999999999998, 
   "ka": "0.1511", 
   "target": "GSVIVT01012103001", 
   "evalue": "0.0", 
   "block_score": "271.0", 
   "ks": "1.0463", 
   "source": "Glyma.07G221000"
  }, 
  {
   "distance": 0.45272, 
   "target": "MDP0000003818", 
   "source": "LOC_Os08g43130"
  }, 
  {
   "distance": 0.99489, 
   "target": "Phpat.011G004300", 
   "source": "LOC_Os08g43130"
  }, 
  {
   "distance": 0.43678, 
   "target": "Solyc02g068720.2", 
   "source": "LOC_Os08g43130"
  }, 
  {
   "distance": 0.615, 
   "target": "MDP0000128017", 
   "source": "LOC_Os08g43130"
  }, 
  {
   "distance": 0.51986, 
   "target": "scaffold00062.200", 
   "source": "LOC_Os08g43130"
  }, 
  {
   "distance": 0.44493, 
   "target": "MDP0000443324", 
   "source": "LOC_Os08g43130"
  }, 
  {
   "distance": 0.84939, 
   "target": "GRMZM2G089565", 
   "source": "LOC_Os08g43130"
  }, 
  {
   "distance": 0.62809, 
   "target": "Potri.015G123500", 
   "source": "LOC_Os08g43130"
  }, 
  {
   "distance": 0.48566000000000004, 
   "target": "MDP0000119653", 
   "source": "LOC_Os08g43130"
  }, 
  {
   "distance": 0.71041, 
   "target": "Potri.015G123000", 
   "source": "LOC_Os08g43130"
  }, 
  {
   "distance": 0.42685000000000006, 
   "target": "Thecc1EG006054", 
   "source": "LOC_Os08g43130"
  }, 
  {
   "distance": 0.53879, 
   "target": "Potri.015G124200", 
   "source": "LOC_Os08g43130"
  }, 
  {
   "distance": 0.55735, 
   "target": "Brara.E00925", 
   "source": "LOC_Os08g43130"
  }, 
  {
   "distance": 0.46604000000000007, 
   "target": "Potri.015G123900", 
   "source": "LOC_Os08g43130"
  }, 
  {
   "distance": 0.47313000000000005, 
   "target": "evm.TU.supercontig_30.140", 
   "source": "LOC_Os08g43130"
  }, 
  {
   "distance": 0.45019000000000003, 
   "target": "29840.m000608", 
   "source": "LOC_Os08g43130"
  }, 
  {
   "distance": 0.7582299999999998, 
   "target": "Medtr4g081610", 
   "source": "LOC_Os08g43130"
  }, 
  {
   "distance": 0.15025, 
   "target": "GRMZM5G886363", 
   "source": "LOC_Os08g43130"
  }, 
  {
   "distance": 0.4791, 
   "target": "Glyma.20G019300", 
   "source": "LOC_Os08g43130"
  }, 
  {
   "distance": 0.44395999999999997, 
   "target": "mrna20021", 
   "source": "LOC_Os08g43130"
  }, 
  {
   "distance": 0.5474100000000001, 
   "target": "16037677", 
   "source": "LOC_Os08g43130"
  }, 
  {
   "distance": 0.44164000000000003, 
   "target": "Potri.012G124400", 
   "source": "LOC_Os08g43130"
  }, 
  {
   "distance": 0.59415, 
   "target": "GRMZM2G410812", 
   "source": "LOC_Os08g43130"
  }, 
  {
   "distance": 0.12853, 
   "target": "GRMZM2G180150", 
   "source": "LOC_Os08g43130"
  }, 
  {
   "distance": 0.4374, 
   "target": "Gorai.002G164100", 
   "source": "LOC_Os08g43130"
  }, 
  {
   "distance": 0.6154499999999999, 
   "target": "Potri.015G124000", 
   "source": "LOC_Os08g43130"
  }, 
  {
   "distance": 0.41153, 
   "target": "GSVIVT01012103001", 
   "source": "LOC_Os08g43130"
  }, 
  {
   "distance": 0.94763, 
   "target": "Phpat.011G004300", 
   "source": "MDP0000003818"
  }, 
  {
   "distance": 0.26232, 
   "target": "Solyc02g068720.2", 
   "source": "MDP0000003818"
  }, 
  {
   "distance": 0.19218, 
   "target": "MDP0000128017", 
   "source": "MDP0000003818"
  }, 
  {
   "distance": 0.4726, 
   "target": "scaffold00062.200", 
   "source": "MDP0000003818"
  }, 
  {
   "distance": 0.03931, 
   "target": "MDP0000443324", 
   "source": "MDP0000003818"
  }, 
  {
   "distance": 1.2346500000000002, 
   "target": "GRMZM2G089565", 
   "source": "MDP0000003818"
  }, 
  {
   "distance": 0.37568999999999997, 
   "target": "Potri.015G123500", 
   "source": "MDP0000003818"
  }, 
  {
   "distance": 0.061119999999999994, 
   "target": "MDP0000119653", 
   "source": "MDP0000003818"
  }, 
  {
   "distance": 0.45801, 
   "target": "Potri.015G123000", 
   "source": "MDP0000003818"
  }, 
  {
   "distance": 0.17445, 
   "target": "Thecc1EG006054", 
   "source": "MDP0000003818"
  }, 
  {
   "distance": 0.28639, 
   "target": "Potri.015G124200", 
   "source": "MDP0000003818"
  }, 
  {
   "distance": 0.30495, 
   "target": "Brara.E00925", 
   "source": "MDP0000003818"
  }, 
  {
   "distance": 0.21363999999999997, 
   "target": "Potri.015G123900", 
   "source": "MDP0000003818"
  }, 
  {
   "distance": 0.22072999999999998, 
   "target": "evm.TU.supercontig_30.140", 
   "source": "MDP0000003818"
  }, 
  {
   "distance": 0.19779, 
   "target": "29840.m000608", 
   "source": "MDP0000003818"
  }, 
  {
   "distance": 0.46831, 
   "target": "Medtr4g081610", 
   "source": "MDP0000003818"
  }, 
  {
   "distance": 0.5355099999999999, 
   "target": "GRMZM5G886363", 
   "source": "MDP0000003818"
  }, 
  {
   "distance": 0.18918000000000001, 
   "target": "Glyma.20G019300", 
   "source": "MDP0000003818"
  }, 
  {
   "distance": 0.1043, 
   "target": "mrna20021", 
   "source": "MDP0000003818"
  }, 
  {
   "distance": 0.29501, 
   "target": "16037677", 
   "source": "MDP0000003818"
  }, 
  {
   "distance": 0.18924, 
   "target": "Potri.012G124400", 
   "source": "MDP0000003818"
  }, 
  {
   "distance": 0.9794099999999999, 
   "target": "GRMZM2G410812", 
   "source": "MDP0000003818"
  }, 
  {
   "distance": 0.47849, 
   "target": "GRMZM2G180150", 
   "source": "MDP0000003818"
  }, 
  {
   "distance": 0.185, 
   "target": "Gorai.002G164100", 
   "source": "MDP0000003818"
  }, 
  {
   "distance": 0.36305, 
   "target": "Potri.015G124000", 
   "source": "MDP0000003818"
  }, 
  {
   "distance": 0.19065, 
   "target": "GSVIVT01012103001", 
   "source": "MDP0000003818"
  }, 
  {
   "distance": 0.93169, 
   "target": "Solyc02g068720.2", 
   "source": "Phpat.011G004300"
  }, 
  {
   "distance": 1.1099100000000002, 
   "target": "MDP0000128017", 
   "source": "Phpat.011G004300"
  }, 
  {
   "distance": 0.8698899999999999, 
   "target": "scaffold00062.200", 
   "source": "Phpat.011G004300"
  }, 
  {
   "distance": 0.93984, 
   "target": "MDP0000443324", 
   "source": "Phpat.011G004300"
  }, 
  {
   "distance": 1.77682, 
   "target": "GRMZM2G089565", 
   "source": "Phpat.011G004300"
  }, 
  {
   "distance": 1.123, 
   "target": "Potri.015G123500", 
   "source": "Phpat.011G004300"
  }, 
  {
   "distance": 0.9805699999999999, 
   "target": "MDP0000119653", 
   "source": "Phpat.011G004300"
  }, 
  {
   "distance": 1.2053199999999997, 
   "target": "Potri.015G123000", 
   "source": "Phpat.011G004300"
  }, 
  {
   "distance": 0.9217599999999998, 
   "target": "Thecc1EG006054", 
   "source": "Phpat.011G004300"
  }, 
  {
   "distance": 1.0336999999999998, 
   "target": "Potri.015G124200", 
   "source": "Phpat.011G004300"
  }, 
  {
   "distance": 1.0522599999999998, 
   "target": "Brara.E00925", 
   "source": "Phpat.011G004300"
  }, 
  {
   "distance": 0.9609499999999997, 
   "target": "Potri.015G123900", 
   "source": "Phpat.011G004300"
  }, 
  {
   "distance": 0.9680399999999998, 
   "target": "evm.TU.supercontig_30.140", 
   "source": "Phpat.011G004300"
  }, 
  {
   "distance": 0.9450999999999997, 
   "target": "29840.m000608", 
   "source": "Phpat.011G004300"
  }, 
  {
   "distance": 1.2531400000000001, 
   "target": "Medtr4g081610", 
   "source": "Phpat.011G004300"
  }, 
  {
   "distance": 1.07768, 
   "target": "GRMZM5G886363", 
   "source": "Phpat.011G004300"
  }, 
  {
   "distance": 0.9740099999999998, 
   "target": "Glyma.20G019300", 
   "source": "Phpat.011G004300"
  }, 
  {
   "distance": 0.9388699999999999, 
   "target": "mrna20021", 
   "source": "Phpat.011G004300"
  }, 
  {
   "distance": 1.0423199999999997, 
   "target": "16037677", 
   "source": "Phpat.011G004300"
  }, 
  {
   "distance": 0.9365499999999998, 
   "target": "Potri.012G124400", 
   "source": "Phpat.011G004300"
  }, 
  {
   "distance": 1.52158, 
   "target": "GRMZM2G410812", 
   "source": "Phpat.011G004300"
  }, 
  {
   "distance": 1.02066, 
   "target": "GRMZM2G180150", 
   "source": "Phpat.011G004300"
  }, 
  {
   "distance": 0.9323099999999999, 
   "target": "Gorai.002G164100", 
   "source": "Phpat.011G004300"
  }, 
  {
   "distance": 1.11036, 
   "target": "Potri.015G124000", 
   "source": "Phpat.011G004300"
  }, 
  {
   "distance": 0.90644, 
   "target": "GSVIVT01012103001", 
   "source": "Phpat.011G004300"
  }, 
  {
   "distance": 0.9634699999999999, 
   "target": "GRMZM2G410812", 
   "source": "Solyc02g068720.2"
  }, 
  {
   "distance": 0.42460000000000003, 
   "target": "MDP0000128017", 
   "source": "Solyc02g068720.2"
  }, 
  {
   "distance": 0.45666, 
   "target": "scaffold00062.200", 
   "source": "Solyc02g068720.2"
  }, 
  {
   "distance": 0.25453000000000003, 
   "target": "MDP0000443324", 
   "source": "Solyc02g068720.2"
  }, 
  {
   "distance": 1.2187100000000002, 
   "target": "GRMZM2G089565", 
   "source": "Solyc02g068720.2"
  }, 
  {
   "distance": 0.43768999999999997, 
   "target": "Potri.015G123500", 
   "source": "Solyc02g068720.2"
  }, 
  {
   "distance": 0.29525999999999997, 
   "target": "MDP0000119653", 
   "source": "Solyc02g068720.2"
  }, 
  {
   "distance": 0.52001, 
   "ka": "0.2245", 
   "target": "Potri.015G123000", 
   "evalue": "5e-26", 
   "block_score": "1024.0", 
   "ks": "0.9854", 
   "source": "Solyc02g068720.2"
  }, 
  {
   "distance": 0.23645, 
   "ka": "0.1089", 
   "target": "Thecc1EG006054", 
   "evalue": "0.0", 
   "block_score": "500.0", 
   "ks": "1.3735", 
   "source": "Solyc02g068720.2"
  }, 
  {
   "distance": 0.34839, 
   "target": "Potri.015G124200", 
   "source": "Solyc02g068720.2"
  }, 
  {
   "distance": 0.27564, 
   "target": "Potri.015G123900", 
   "source": "Solyc02g068720.2"
  }, 
  {
   "distance": 0.28273000000000004, 
   "ka": "0.1229", 
   "target": "evm.TU.supercontig_30.140", 
   "evalue": "0.0", 
   "block_score": "425.0", 
   "ks": "1.5849", 
   "source": "Solyc02g068720.2"
  }, 
  {
   "distance": 0.247, 
   "target": "Gorai.002G164100", 
   "source": "Solyc02g068720.2"
  }, 
  {
   "distance": 0.5678300000000001, 
   "target": "Medtr4g081610", 
   "source": "Solyc02g068720.2"
  }, 
  {
   "distance": 0.51957, 
   "target": "GRMZM5G886363", 
   "source": "Solyc02g068720.2"
  }, 
  {
   "distance": 0.28869999999999996, 
   "ka": "0.1326", 
   "target": "Glyma.20G019300", 
   "evalue": "0.0", 
   "block_score": "554.0", 
   "ks": "1.458", 
   "source": "Solyc02g068720.2"
  }, 
  {
   "distance": 0.25356, 
   "ka": "0.1167", 
   "target": "mrna20021", 
   "evalue": "0.0", 
   "block_score": "1903.0", 
   "ks": "1.6104", 
   "source": "Solyc02g068720.2"
  }, 
  {
   "distance": 0.35701, 
   "ka": "0.1442", 
   "target": "16037677", 
   "evalue": "0.0", 
   "block_score": "305.0", 
   "ks": "3.4436", 
   "source": "Solyc02g068720.2"
  }, 
  {
   "distance": 0.25123999999999996, 
   "ka": "0.1125", 
   "target": "Potri.012G124400", 
   "evalue": "0.0", 
   "block_score": "918.0", 
   "ks": "1.3063", 
   "source": "Solyc02g068720.2"
  }, 
  {
   "distance": 0.22113, 
   "ka": "0.1064", 
   "target": "GSVIVT01012103001", 
   "evalue": "0.0", 
   "block_score": "538.0", 
   "ks": "1.254", 
   "source": "Solyc02g068720.2"
  }, 
  {
   "distance": 0.46255, 
   "target": "GRMZM2G180150", 
   "source": "Solyc02g068720.2"
  }, 
  {
   "distance": 0.25978999999999997, 
   "ka": "0.0882", 
   "target": "29840.m000608", 
   "evalue": "0.0", 
   "block_score": "229.0", 
   "ks": "1.6958", 
   "source": "Solyc02g068720.2"
  }, 
  {
   "distance": 0.42505, 
   "target": "Potri.015G124000", 
   "source": "Solyc02g068720.2"
  }, 
  {
   "distance": 0.36695000000000005, 
   "ka": "0.1498", 
   "target": "Brara.E00925", 
   "evalue": "0.0", 
   "block_score": "225.0", 
   "ks": "3.0987", 
   "source": "Solyc02g068720.2"
  }, 
  {
   "distance": 0.6348799999999999, 
   "target": "scaffold00062.200", 
   "source": "MDP0000128017"
  }, 
  {
   "distance": 0.20159, 
   "target": "MDP0000443324", 
   "source": "MDP0000128017"
  }, 
  {
   "distance": 1.3969299999999998, 
   "target": "GRMZM2G089565", 
   "source": "MDP0000128017"
  }, 
  {
   "distance": 0.53797, 
   "target": "Potri.015G123500", 
   "source": "MDP0000128017"
  }, 
  {
   "distance": 0.22512000000000001, 
   "target": "MDP0000119653", 
   "source": "MDP0000128017"
  }, 
  {
   "distance": 0.6202899999999999, 
   "target": "Potri.015G123000", 
   "source": "MDP0000128017"
  }, 
  {
   "distance": 0.33673000000000003, 
   "target": "Thecc1EG006054", 
   "source": "MDP0000128017"
  }, 
  {
   "distance": 0.44867, 
   "target": "Potri.015G124200", 
   "source": "MDP0000128017"
  }, 
  {
   "distance": 0.46723000000000003, 
   "target": "Brara.E00925", 
   "source": "MDP0000128017"
  }, 
  {
   "distance": 0.37592000000000003, 
   "target": "Potri.015G123900", 
   "source": "MDP0000128017"
  }, 
  {
   "distance": 0.38301, 
   "target": "evm.TU.supercontig_30.140", 
   "source": "MDP0000128017"
  }, 
  {
   "distance": 0.36007, 
   "target": "29840.m000608", 
   "source": "MDP0000128017"
  }, 
  {
   "distance": 0.6305899999999999, 
   "target": "Medtr4g081610", 
   "source": "MDP0000128017"
  }, 
  {
   "distance": 0.6977899999999999, 
   "target": "GRMZM5G886363", 
   "source": "MDP0000128017"
  }, 
  {
   "distance": 0.35146, 
   "target": "Glyma.20G019300", 
   "source": "MDP0000128017"
  }, 
  {
   "distance": 0.26658, 
   "target": "mrna20021", 
   "source": "MDP0000128017"
  }, 
  {
   "distance": 0.45729000000000003, 
   "target": "16037677", 
   "source": "MDP0000128017"
  }, 
  {
   "distance": 0.35152, 
   "target": "Potri.012G124400", 
   "source": "MDP0000128017"
  }, 
  {
   "distance": 1.14169, 
   "target": "GRMZM2G410812", 
   "source": "MDP0000128017"
  }, 
  {
   "distance": 0.64077, 
   "target": "GRMZM2G180150", 
   "source": "MDP0000128017"
  }, 
  {
   "distance": 0.34728000000000003, 
   "target": "Gorai.002G164100", 
   "source": "MDP0000128017"
  }, 
  {
   "distance": 0.52533, 
   "target": "Potri.015G124000", 
   "source": "MDP0000128017"
  }, 
  {
   "distance": 0.35293, 
   "target": "GSVIVT01012103001", 
   "source": "MDP0000128017"
  }, 
  {
   "distance": 0.46481, 
   "target": "MDP0000443324", 
   "source": "scaffold00062.200"
  }, 
  {
   "distance": 1.30179, 
   "target": "GRMZM2G089565", 
   "source": "scaffold00062.200"
  }, 
  {
   "distance": 0.6479699999999999, 
   "target": "Potri.015G123500", 
   "source": "scaffold00062.200"
  }, 
  {
   "distance": 0.50554, 
   "target": "MDP0000119653", 
   "source": "scaffold00062.200"
  }, 
  {
   "distance": 0.7302899999999999, 
   "target": "Potri.015G123000", 
   "source": "scaffold00062.200"
  }, 
  {
   "distance": 0.44673, 
   "target": "Thecc1EG006054", 
   "source": "scaffold00062.200"
  }, 
  {
   "distance": 0.55867, 
   "target": "Potri.015G124200", 
   "source": "scaffold00062.200"
  }, 
  {
   "distance": 0.57723, 
   "target": "Brara.E00925", 
   "source": "scaffold00062.200"
  }, 
  {
   "distance": 0.48592, 
   "target": "Potri.015G123900", 
   "source": "scaffold00062.200"
  }, 
  {
   "distance": 0.49301, 
   "target": "evm.TU.supercontig_30.140", 
   "source": "scaffold00062.200"
  }, 
  {
   "distance": 0.47007, 
   "target": "29840.m000608", 
   "source": "scaffold00062.200"
  }, 
  {
   "distance": 0.77811, 
   "target": "Medtr4g081610", 
   "source": "scaffold00062.200"
  }, 
  {
   "distance": 0.6026500000000001, 
   "target": "GRMZM5G886363", 
   "source": "scaffold00062.200"
  }, 
  {
   "distance": 0.49898, 
   "target": "Glyma.20G019300", 
   "source": "scaffold00062.200"
  }, 
  {
   "distance": 0.46384, 
   "target": "mrna20021", 
   "source": "scaffold00062.200"
  }, 
  {
   "distance": 0.56729, 
   "target": "16037677", 
   "source": "scaffold00062.200"
  }, 
  {
   "distance": 0.46152, 
   "target": "Potri.012G124400", 
   "source": "scaffold00062.200"
  }, 
  {
   "distance": 1.04655, 
   "target": "GRMZM2G410812", 
   "source": "scaffold00062.200"
  }, 
  {
   "distance": 0.5456300000000001, 
   "target": "GRMZM2G180150", 
   "source": "scaffold00062.200"
  }, 
  {
   "distance": 0.45728, 
   "target": "Gorai.002G164100", 
   "source": "scaffold00062.200"
  }, 
  {
   "distance": 0.63533, 
   "target": "Potri.015G124000", 
   "source": "scaffold00062.200"
  }, 
  {
   "distance": 0.43141, 
   "target": "GSVIVT01012103001", 
   "source": "scaffold00062.200"
  }, 
  {
   "distance": 1.2268600000000003, 
   "target": "GRMZM2G089565", 
   "source": "MDP0000443324"
  }, 
  {
   "distance": 0.3679, 
   "target": "Potri.015G123500", 
   "source": "MDP0000443324"
  }, 
  {
   "distance": 0.07225, 
   "target": "MDP0000119653", 
   "source": "MDP0000443324"
  }, 
  {
   "distance": 0.45022, 
   "target": "Potri.015G123000", 
   "source": "MDP0000443324"
  }, 
  {
   "distance": 0.16665999999999997, 
   "target": "Thecc1EG006054", 
   "source": "MDP0000443324"
  }, 
  {
   "distance": 0.2786, 
   "target": "Potri.015G124200", 
   "source": "MDP0000443324"
  }, 
  {
   "distance": 0.29716000000000004, 
   "target": "Brara.E00925", 
   "source": "MDP0000443324"
  }, 
  {
   "distance": 0.20584999999999998, 
   "target": "Potri.015G123900", 
   "source": "MDP0000443324"
  }, 
  {
   "distance": 0.21293999999999996, 
   "target": "evm.TU.supercontig_30.140", 
   "source": "MDP0000443324"
  }, 
  {
   "distance": 0.19, 
   "target": "29840.m000608", 
   "source": "MDP0000443324"
  }, 
  {
   "distance": 0.46052, 
   "target": "Medtr4g081610", 
   "source": "MDP0000443324"
  }, 
  {
   "distance": 0.5277200000000001, 
   "target": "GRMZM5G886363", 
   "source": "MDP0000443324"
  }, 
  {
   "distance": 0.18139, 
   "target": "Glyma.20G019300", 
   "source": "MDP0000443324"
  }, 
  {
   "distance": 0.09651000000000001, 
   "target": "mrna20021", 
   "source": "MDP0000443324"
  }, 
  {
   "distance": 0.28722, 
   "target": "16037677", 
   "source": "MDP0000443324"
  }, 
  {
   "distance": 0.18145, 
   "target": "Potri.012G124400", 
   "source": "MDP0000443324"
  }, 
  {
   "distance": 0.9716199999999999, 
   "target": "GRMZM2G410812", 
   "source": "MDP0000443324"
  }, 
  {
   "distance": 0.4707, 
   "target": "GRMZM2G180150", 
   "source": "MDP0000443324"
  }, 
  {
   "distance": 0.17720999999999998, 
   "target": "Gorai.002G164100", 
   "source": "MDP0000443324"
  }, 
  {
   "distance": 0.35525999999999996, 
   "target": "Potri.015G124000", 
   "source": "MDP0000443324"
  }, 
  {
   "distance": 0.18286000000000002, 
   "target": "GSVIVT01012103001", 
   "source": "MDP0000443324"
  }, 
  {
   "distance": 1.41002, 
   "target": "Potri.015G123500", 
   "source": "GRMZM2G089565"
  }, 
  {
   "distance": 1.2675900000000002, 
   "target": "MDP0000119653", 
   "source": "GRMZM2G089565"
  }, 
  {
   "distance": 1.49234, 
   "target": "Potri.015G123000", 
   "source": "GRMZM2G089565"
  }, 
  {
   "distance": 1.20878, 
   "target": "Thecc1EG006054", 
   "source": "GRMZM2G089565"
  }, 
  {
   "distance": 1.32072, 
   "target": "Potri.015G124200", 
   "source": "GRMZM2G089565"
  }, 
  {
   "distance": 1.3392799999999998, 
   "target": "Brara.E00925", 
   "source": "GRMZM2G089565"
  }, 
  {
   "distance": 1.2479699999999998, 
   "target": "Potri.015G123900", 
   "source": "GRMZM2G089565"
  }, 
  {
   "distance": 1.2550599999999998, 
   "target": "evm.TU.supercontig_30.140", 
   "source": "GRMZM2G089565"
  }, 
  {
   "distance": 1.23212, 
   "target": "29840.m000608", 
   "source": "GRMZM2G089565"
  }, 
  {
   "distance": 1.5401599999999998, 
   "target": "Medtr4g081610", 
   "source": "GRMZM2G089565"
  }, 
  {
   "distance": 0.70024, 
   "target": "GRMZM5G886363", 
   "source": "GRMZM2G089565"
  }, 
  {
   "distance": 1.2610300000000003, 
   "target": "Glyma.20G019300", 
   "source": "GRMZM2G089565"
  }, 
  {
   "distance": 1.2258900000000001, 
   "target": "mrna20021", 
   "source": "GRMZM2G089565"
  }, 
  {
   "distance": 1.32934, 
   "target": "16037677", 
   "source": "GRMZM2G089565"
  }, 
  {
   "distance": 1.22357, 
   "target": "Potri.012G124400", 
   "source": "GRMZM2G089565"
  }, 
  {
   "distance": 0.66548, 
   "target": "GRMZM2G410812", 
   "source": "GRMZM2G089565"
  }, 
  {
   "distance": 0.91046, 
   "target": "GRMZM2G180150", 
   "source": "GRMZM2G089565"
  }, 
  {
   "distance": 1.21933, 
   "target": "Gorai.002G164100", 
   "source": "GRMZM2G089565"
  }, 
  {
   "distance": 1.39738, 
   "target": "Potri.015G124000", 
   "source": "GRMZM2G089565"
  }, 
  {
   "distance": 1.19346, 
   "target": "GSVIVT01012103001", 
   "source": "GRMZM2G089565"
  }, 
  {
   "distance": 0.40863, 
   "target": "MDP0000119653", 
   "source": "Potri.015G123500"
  }, 
  {
   "distance": 0.60132, 
   "target": "Potri.015G123000", 
   "source": "Potri.015G123500"
  }, 
  {
   "distance": 0.31776, 
   "target": "Thecc1EG006054", 
   "source": "Potri.015G123500"
  }, 
  {
   "distance": 0.29004, 
   "target": "Potri.015G124200", 
   "source": "Potri.015G123500"
  }, 
  {
   "distance": 0.42868, 
   "target": "Brara.E00925", 
   "source": "Potri.015G123500"
  }, 
  {
   "distance": 0.21729, 
   "target": "Potri.015G123900", 
   "source": "Potri.015G123500"
  }, 
  {
   "distance": 0.34446000000000004, 
   "target": "evm.TU.supercontig_30.140", 
   "source": "Potri.015G123500"
  }, 
  {
   "distance": 0.26506, 
   "target": "29840.m000608", 
   "source": "Potri.015G123500"
  }, 
  {
   "distance": 0.6811999999999999, 
   "target": "Medtr4g081610", 
   "source": "Potri.015G123500"
  }, 
  {
   "distance": 0.71088, 
   "target": "GRMZM5G886363", 
   "source": "Potri.015G123500"
  }, 
  {
   "distance": 0.40207000000000004, 
   "target": "Glyma.20G019300", 
   "source": "Potri.015G123500"
  }, 
  {
   "distance": 0.36693, 
   "target": "mrna20021", 
   "source": "Potri.015G123500"
  }, 
  {
   "distance": 0.41874000000000006, 
   "target": "16037677", 
   "source": "Potri.015G123500"
  }, 
  {
   "distance": 0.23033000000000003, 
   "target": "Potri.012G124400", 
   "source": "Potri.015G123500"
  }, 
  {
   "distance": 1.1547800000000001, 
   "target": "GRMZM2G410812", 
   "source": "Potri.015G123500"
  }, 
  {
   "distance": 0.65386, 
   "target": "GRMZM2G180150", 
   "source": "Potri.015G123500"
  }, 
  {
   "distance": 0.32831, 
   "target": "Gorai.002G164100", 
   "source": "Potri.015G123500"
  }, 
  {
   "distance": 0.18378, 
   "target": "Potri.015G124000", 
   "source": "Potri.015G123500"
  }, 
  {
   "distance": 0.36602, 
   "target": "GSVIVT01012103001", 
   "source": "Potri.015G123500"
  }, 
  {
   "distance": 0.49095, 
   "target": "Potri.015G123000", 
   "source": "MDP0000119653"
  }, 
  {
   "distance": 0.20739000000000002, 
   "target": "Thecc1EG006054", 
   "source": "MDP0000119653"
  }, 
  {
   "distance": 0.31933, 
   "target": "Potri.015G124200", 
   "source": "MDP0000119653"
  }, 
  {
   "distance": 0.33789, 
   "target": "Brara.E00925", 
   "source": "MDP0000119653"
  }, 
  {
   "distance": 0.24657999999999997, 
   "target": "Potri.015G123900", 
   "source": "MDP0000119653"
  }, 
  {
   "distance": 0.25366999999999995, 
   "target": "evm.TU.supercontig_30.140", 
   "source": "MDP0000119653"
  }, 
  {
   "distance": 0.23072999999999996, 
   "target": "29840.m000608", 
   "source": "MDP0000119653"
  }, 
  {
   "distance": 0.50125, 
   "target": "Medtr4g081610", 
   "source": "MDP0000119653"
  }, 
  {
   "distance": 0.56845, 
   "target": "GRMZM5G886363", 
   "source": "MDP0000119653"
  }, 
  {
   "distance": 0.22211999999999998, 
   "target": "Glyma.20G019300", 
   "source": "MDP0000119653"
  }, 
  {
   "distance": 0.13724, 
   "target": "mrna20021", 
   "source": "MDP0000119653"
  }, 
  {
   "distance": 0.32795, 
   "target": "16037677", 
   "source": "MDP0000119653"
  }, 
  {
   "distance": 0.22218, 
   "target": "Potri.012G124400", 
   "source": "MDP0000119653"
  }, 
  {
   "distance": 1.0123499999999999, 
   "target": "GRMZM2G410812", 
   "source": "MDP0000119653"
  }, 
  {
   "distance": 0.51143, 
   "target": "GRMZM2G180150", 
   "source": "MDP0000119653"
  }, 
  {
   "distance": 0.21793999999999997, 
   "target": "Gorai.002G164100", 
   "source": "MDP0000119653"
  }, 
  {
   "distance": 0.39598999999999995, 
   "target": "Potri.015G124000", 
   "source": "MDP0000119653"
  }, 
  {
   "distance": 0.22359, 
   "target": "GSVIVT01012103001", 
   "source": "MDP0000119653"
  }, 
  {
   "distance": 0.3321, 
   "ka": "0.2096", 
   "target": "Thecc1EG006054", 
   "evalue": "2e-26", 
   "block_score": "309.0", 
   "ks": "0.8398", 
   "source": "Potri.015G123000"
  }, 
  {
   "distance": 0.51202, 
   "target": "Potri.015G124200", 
   "source": "Potri.015G123000"
  }, 
  {
   "distance": 0.5305799999999999, 
   "target": "Brara.E00925", 
   "source": "Potri.015G123000"
  }, 
  {
   "distance": 0.43927000000000005, 
   "target": "Potri.015G123900", 
   "source": "Potri.015G123000"
  }, 
  {
   "distance": 0.44636000000000003, 
   "ka": "0.2242", 
   "target": "evm.TU.supercontig_30.140", 
   "evalue": "4e-24", 
   "block_score": "227.0", 
   "ks": "0.8013", 
   "source": "Potri.015G123000"
  }, 
  {
   "distance": 0.42342, 
   "target": "29840.m000608", 
   "source": "Potri.015G123000"
  }, 
  {
   "distance": 0.76352, 
   "target": "Medtr4g081610", 
   "source": "Potri.015G123000"
  }, 
  {
   "distance": 0.7931999999999999, 
   "target": "GRMZM5G886363", 
   "source": "Potri.015G123000"
  }, 
  {
   "distance": 0.48439, 
   "target": "Glyma.20G019300", 
   "source": "Potri.015G123000"
  }, 
  {
   "distance": 0.44925, 
   "ka": "0.1625", 
   "target": "mrna20021", 
   "evalue": "1e-24", 
   "block_score": "1228.0", 
   "ks": "1.0142", 
   "source": "Potri.015G123000"
  }, 
  {
   "distance": 0.52064, 
   "target": "16037677", 
   "source": "Potri.015G123000"
  }, 
  {
   "distance": 0.41487, 
   "ka": "0.2027", 
   "target": "Potri.012G124400", 
   "evalue": "2e-26", 
   "block_score": "21253.0", 
   "ks": "0.6233", 
   "source": "Potri.015G123000"
  }, 
  {
   "distance": 1.2370999999999999, 
   "target": "GRMZM2G410812", 
   "source": "Potri.015G123000"
  }, 
  {
   "distance": 0.73618, 
   "target": "GRMZM2G180150", 
   "source": "Potri.015G123000"
  }, 
  {
   "distance": 0.34433, 
   "target": "Gorai.002G164100", 
   "source": "Potri.015G123000"
  }, 
  {
   "distance": 0.58868, 
   "target": "Potri.015G124000", 
   "source": "Potri.015G123000"
  }, 
  {
   "distance": 0.44834, 
   "ka": "0.1793", 
   "target": "GSVIVT01012103001", 
   "evalue": "2e-26", 
   "block_score": "302.0", 
   "ks": "1.101", 
   "source": "Potri.015G123000"
  }, 
  {
   "distance": 0.9535399999999999, 
   "target": "GRMZM2G410812", 
   "source": "Thecc1EG006054"
  }, 
  {
   "distance": 0.22846, 
   "target": "Potri.015G124200", 
   "source": "Thecc1EG006054"
  }, 
  {
   "distance": 0.15571, 
   "target": "Potri.015G123900", 
   "source": "Thecc1EG006054"
  }, 
  {
   "distance": 0.16279999999999997, 
   "ka": "0.0729", 
   "target": "evm.TU.supercontig_30.140", 
   "evalue": "0.0", 
   "block_score": "1368.0", 
   "ks": "0.8495", 
   "source": "Thecc1EG006054"
  }, 
  {
   "distance": 0.06077, 
   "target": "Gorai.002G164100", 
   "source": "Thecc1EG006054"
  }, 
  {
   "distance": 0.47996, 
   "target": "Medtr4g081610", 
   "source": "Thecc1EG006054"
  }, 
  {
   "distance": 0.5096400000000001, 
   "target": "GRMZM5G886363", 
   "source": "Thecc1EG006054"
  }, 
  {
   "distance": 0.20083, 
   "target": "Glyma.20G019300", 
   "source": "Thecc1EG006054"
  }, 
  {
   "distance": 0.16568999999999998, 
   "ka": "0.0778", 
   "target": "mrna20021", 
   "evalue": "0.0", 
   "block_score": "1559.0", 
   "ks": "1.0039", 
   "source": "Thecc1EG006054"
  }, 
  {
   "distance": 0.23707999999999996, 
   "ka": "0.1", 
   "target": "16037677", 
   "evalue": "0.0", 
   "block_score": "364.0", 
   "ks": "1.4476", 
   "source": "Thecc1EG006054"
  }, 
  {
   "distance": 0.13130999999999998, 
   "ka": "0.0629", 
   "target": "Potri.012G124400", 
   "evalue": "0.0", 
   "block_score": "269.0", 
   "ks": "0.7849", 
   "source": "Thecc1EG006054"
  }, 
  {
   "distance": 0.24701999999999996, 
   "ka": "0.1049", 
   "target": "Brara.E00925", 
   "evalue": "0.0", 
   "block_score": "364.0", 
   "ks": "1.5272", 
   "source": "Thecc1EG006054"
  }, 
  {
   "distance": 0.45262, 
   "target": "GRMZM2G180150", 
   "source": "Thecc1EG006054"
  }, 
  {
   "distance": 0.13985999999999998, 
   "ka": "0.0473", 
   "target": "29840.m000608", 
   "evalue": "0.0", 
   "block_score": "308.0", 
   "ks": "0.8096", 
   "source": "Thecc1EG006054"
  }, 
  {
   "distance": 0.30512, 
   "target": "Potri.015G124000", 
   "source": "Thecc1EG006054"
  }, 
  {
   "distance": 0.16477999999999998, 
   "ka": "0.0738", 
   "target": "GSVIVT01012103001", 
   "evalue": "0.0", 
   "block_score": "1044.0", 
   "ks": "0.8079", 
   "source": "Thecc1EG006054"
  }, 
  {
   "distance": 0.33938, 
   "target": "Brara.E00925", 
   "source": "Potri.015G124200"
  }, 
  {
   "distance": 0.09935, 
   "target": "Potri.015G123900", 
   "source": "Potri.015G124200"
  }, 
  {
   "distance": 0.25516, 
   "target": "evm.TU.supercontig_30.140", 
   "source": "Potri.015G124200"
  }, 
  {
   "distance": 0.17575999999999997, 
   "target": "29840.m000608", 
   "source": "Potri.015G124200"
  }, 
  {
   "distance": 0.5919, 
   "target": "Medtr4g081610", 
   "source": "Potri.015G124200"
  }, 
  {
   "distance": 0.6215799999999999, 
   "target": "GRMZM5G886363", 
   "source": "Potri.015G124200"
  }, 
  {
   "distance": 0.31277, 
   "target": "Glyma.20G019300", 
   "source": "Potri.015G124200"
  }, 
  {
   "distance": 0.27763, 
   "target": "mrna20021", 
   "source": "Potri.015G124200"
  }, 
  {
   "distance": 0.32944, 
   "target": "16037677", 
   "source": "Potri.015G124200"
  }, 
  {
   "distance": 0.14103, 
   "target": "Potri.012G124400", 
   "source": "Potri.015G124200"
  }, 
  {
   "distance": 1.0654799999999998, 
   "target": "GRMZM2G410812", 
   "source": "Potri.015G124200"
  }, 
  {
   "distance": 0.56456, 
   "target": "GRMZM2G180150", 
   "source": "Potri.015G124200"
  }, 
  {
   "distance": 0.23901, 
   "target": "Gorai.002G164100", 
   "source": "Potri.015G124200"
  }, 
  {
   "distance": 0.2774, 
   "target": "Potri.015G124000", 
   "source": "Potri.015G124200"
  }, 
  {
   "distance": 0.27672, 
   "target": "GSVIVT01012103001", 
   "source": "Potri.015G124200"
  }, 
  {
   "distance": 0.26663, 
   "target": "Potri.015G123900", 
   "source": "Brara.E00925"
  }, 
  {
   "distance": 0.23293999999999998, 
   "target": "evm.TU.supercontig_30.140", 
   "source": "Brara.E00925"
  }, 
  {
   "distance": 0.25078, 
   "target": "29840.m000608", 
   "source": "Brara.E00925"
  }, 
  {
   "distance": 0.61046, 
   "target": "Medtr4g081610", 
   "source": "Brara.E00925"
  }, 
  {
   "distance": 0.64014, 
   "target": "GRMZM5G886363", 
   "source": "Brara.E00925"
  }, 
  {
   "distance": 0.33132999999999996, 
   "target": "Glyma.20G019300", 
   "source": "Brara.E00925"
  }, 
  {
   "distance": 0.29619, 
   "ka": "0.1179", 
   "target": "mrna20021", 
   "evalue": "0.0", 
   "block_score": "339.0", 
   "ks": "1.953", 
   "source": "Brara.E00925"
  }, 
  {
   "distance": 0.0427, 
   "ka": "0.0191", 
   "target": "16037677", 
   "evalue": "0.0", 
   "block_score": "14181.0", 
   "ks": "0.3276", 
   "source": "Brara.E00925"
  }, 
  {
   "distance": 0.24222999999999997, 
   "target": "Potri.012G124400", 
   "source": "Brara.E00925"
  }, 
  {
   "distance": 1.08404, 
   "target": "GRMZM2G410812", 
   "source": "Brara.E00925"
  }, 
  {
   "distance": 0.58312, 
   "target": "GRMZM2G180150", 
   "source": "Brara.E00925"
  }, 
  {
   "distance": 0.25756999999999997, 
   "target": "Gorai.002G164100", 
   "source": "Brara.E00925"
  }, 
  {
   "distance": 0.41603999999999997, 
   "target": "Potri.015G124000", 
   "source": "Brara.E00925"
  }, 
  {
   "distance": 0.29528, 
   "ka": "0.1268", 
   "target": "GSVIVT01012103001", 
   "evalue": "0.0", 
   "block_score": "290.0", 
   "ks": "1.5714", 
   "source": "Brara.E00925"
  }, 
  {
   "distance": 0.18241, 
   "target": "evm.TU.supercontig_30.140", 
   "source": "Potri.015G123900"
  }, 
  {
   "distance": 0.10301, 
   "target": "29840.m000608", 
   "source": "Potri.015G123900"
  }, 
  {
   "distance": 0.51915, 
   "target": "Medtr4g081610", 
   "source": "Potri.015G123900"
  }, 
  {
   "distance": 0.54883, 
   "target": "GRMZM5G886363", 
   "source": "Potri.015G123900"
  }, 
  {
   "distance": 0.24002, 
   "target": "Glyma.20G019300", 
   "source": "Potri.015G123900"
  }, 
  {
   "distance": 0.20487999999999998, 
   "target": "mrna20021", 
   "source": "Potri.015G123900"
  }, 
  {
   "distance": 0.25669, 
   "target": "16037677", 
   "source": "Potri.015G123900"
  }, 
  {
   "distance": 0.06828000000000001, 
   "target": "Potri.012G124400", 
   "source": "Potri.015G123900"
  }, 
  {
   "distance": 0.9927299999999999, 
   "target": "GRMZM2G410812", 
   "source": "Potri.015G123900"
  }, 
  {
   "distance": 0.49181, 
   "target": "GRMZM2G180150", 
   "source": "Potri.015G123900"
  }, 
  {
   "distance": 0.16626, 
   "target": "Gorai.002G164100", 
   "source": "Potri.015G123900"
  }, 
  {
   "distance": 0.20465, 
   "target": "Potri.015G124000", 
   "source": "Potri.015G123900"
  }, 
  {
   "distance": 0.20396999999999998, 
   "target": "GSVIVT01012103001", 
   "source": "Potri.015G123900"
  }, 
  {
   "distance": 0.17334999999999998, 
   "target": "Gorai.002G164100", 
   "source": "evm.TU.supercontig_30.140"
  }, 
  {
   "distance": 0.52624, 
   "target": "Medtr4g081610", 
   "source": "evm.TU.supercontig_30.140"
  }, 
  {
   "distance": 0.55592, 
   "target": "GRMZM5G886363", 
   "source": "evm.TU.supercontig_30.140"
  }, 
  {
   "distance": 0.24711, 
   "target": "Glyma.20G019300", 
   "source": "evm.TU.supercontig_30.140"
  }, 
  {
   "distance": 0.21196999999999996, 
   "ka": "0.1018", 
   "target": "mrna20021", 
   "evalue": "0.0", 
   "block_score": "1390.0", 
   "ks": "1.012", 
   "source": "evm.TU.supercontig_30.140"
  }, 
  {
   "distance": 0.22299999999999998, 
   "target": "16037677", 
   "source": "evm.TU.supercontig_30.140"
  }, 
  {
   "distance": 0.15800999999999998, 
   "target": "Potri.012G124400", 
   "source": "evm.TU.supercontig_30.140"
  }, 
  {
   "distance": 0.9998199999999999, 
   "target": "GRMZM2G410812", 
   "source": "evm.TU.supercontig_30.140"
  }, 
  {
   "distance": 0.4989, 
   "target": "GRMZM2G180150", 
   "source": "evm.TU.supercontig_30.140"
  }, 
  {
   "distance": 0.16655999999999999, 
   "ka": "0.0616", 
   "target": "29840.m000608", 
   "evalue": "0.0", 
   "block_score": "232.0", 
   "ks": "0.9497", 
   "source": "evm.TU.supercontig_30.140"
  }, 
  {
   "distance": 0.33182, 
   "target": "Potri.015G124000", 
   "source": "evm.TU.supercontig_30.140"
  }, 
  {
   "distance": 0.21105999999999997, 
   "ka": "0.0937", 
   "target": "GSVIVT01012103001", 
   "evalue": "0.0", 
   "block_score": "979.0", 
   "ks": "0.8793", 
   "source": "evm.TU.supercontig_30.140"
  }, 
  {
   "distance": 0.49051, 
   "target": "Medtr4g081610", 
   "source": "Gorai.002G164100"
  }, 
  {
   "distance": 0.52019, 
   "target": "GRMZM5G886363", 
   "source": "Gorai.002G164100"
  }, 
  {
   "distance": 0.21138, 
   "target": "Glyma.20G019300", 
   "source": "Gorai.002G164100"
  }, 
  {
   "distance": 0.17623999999999998, 
   "target": "mrna20021", 
   "source": "Gorai.002G164100"
  }, 
  {
   "distance": 0.24762999999999996, 
   "target": "16037677", 
   "source": "Gorai.002G164100"
  }, 
  {
   "distance": 0.14185999999999999, 
   "target": "Potri.012G124400", 
   "source": "Gorai.002G164100"
  }, 
  {
   "distance": 0.96409, 
   "target": "GRMZM2G410812", 
   "source": "Gorai.002G164100"
  }, 
  {
   "distance": 0.46316999999999997, 
   "target": "GRMZM2G180150", 
   "source": "Gorai.002G164100"
  }, 
  {
   "distance": 0.15041, 
   "target": "29840.m000608", 
   "source": "Gorai.002G164100"
  }, 
  {
   "distance": 0.31567, 
   "target": "Potri.015G124000", 
   "source": "Gorai.002G164100"
  }, 
  {
   "distance": 0.17532999999999999, 
   "target": "GSVIVT01012103001", 
   "source": "Gorai.002G164100"
  }, 
  {
   "distance": 0.5033, 
   "target": "29840.m000608", 
   "source": "Medtr4g081610"
  }, 
  {
   "distance": 0.84102, 
   "target": "GRMZM5G886363", 
   "source": "Medtr4g081610"
  }, 
  {
   "distance": 0.32816999999999996, 
   "target": "Glyma.20G019300", 
   "source": "Medtr4g081610"
  }, 
  {
   "distance": 0.45954999999999996, 
   "target": "mrna20021", 
   "source": "Medtr4g081610"
  }, 
  {
   "distance": 0.60052, 
   "target": "16037677", 
   "source": "Medtr4g081610"
  }, 
  {
   "distance": 0.49474999999999997, 
   "target": "Potri.012G124400", 
   "source": "Medtr4g081610"
  }, 
  {
   "distance": 1.28492, 
   "target": "GRMZM2G410812", 
   "source": "Medtr4g081610"
  }, 
  {
   "distance": 0.7839999999999999, 
   "target": "GRMZM2G180150", 
   "source": "Medtr4g081610"
  }, 
  {
   "distance": 0.6685599999999999, 
   "target": "Potri.015G124000", 
   "source": "Medtr4g081610"
  }, 
  {
   "distance": 0.49616, 
   "target": "GSVIVT01012103001", 
   "source": "Medtr4g081610"
  }, 
  {
   "distance": 0.53298, 
   "target": "29840.m000608", 
   "source": "GRMZM5G886363"
  }, 
  {
   "distance": 0.56189, 
   "target": "Glyma.20G019300", 
   "source": "GRMZM5G886363"
  }, 
  {
   "distance": 0.52675, 
   "target": "mrna20021", 
   "source": "GRMZM5G886363"
  }, 
  {
   "distance": 0.6302, 
   "target": "16037677", 
   "source": "GRMZM5G886363"
  }, 
  {
   "distance": 0.52443, 
   "target": "Potri.012G124400", 
   "source": "GRMZM5G886363"
  }, 
  {
   "distance": 0.445, 
   "target": "GRMZM2G410812", 
   "source": "GRMZM5G886363"
  }, 
  {
   "distance": 0.21132, 
   "target": "GRMZM2G180150", 
   "source": "GRMZM5G886363"
  }, 
  {
   "distance": 0.69824, 
   "target": "Potri.015G124000", 
   "source": "GRMZM5G886363"
  }, 
  {
   "distance": 0.49432000000000004, 
   "target": "GSVIVT01012103001", 
   "source": "GRMZM5G886363"
  }, 
  {
   "distance": 0.22416999999999998, 
   "target": "29840.m000608", 
   "source": "Glyma.20G019300"
  }, 
  {
   "distance": 0.18042, 
   "ka": "0.087", 
   "target": "mrna20021", 
   "evalue": "0.0", 
   "block_score": "778.0", 
   "ks": "0.9927", 
   "source": "Glyma.20G019300"
  }, 
  {
   "distance": 0.32138999999999995, 
   "target": "16037677", 
   "source": "Glyma.20G019300"
  }, 
  {
   "distance": 0.21561999999999998, 
   "ka": "0.0941", 
   "target": "Potri.012G124400", 
   "evalue": "0.0", 
   "block_score": "367.0", 
   "ks": "1.1245", 
   "source": "Glyma.20G019300"
  }, 
  {
   "distance": 1.00579, 
   "target": "GRMZM2G410812", 
   "source": "Glyma.20G019300"
  }, 
  {
   "distance": 0.50487, 
   "target": "GRMZM2G180150", 
   "source": "Glyma.20G019300"
  }, 
  {
   "distance": 0.38943, 
   "target": "Potri.015G124000", 
   "source": "Glyma.20G019300"
  }, 
  {
   "distance": 0.21703, 
   "ka": "0.097", 
   "target": "GSVIVT01012103001", 
   "evalue": "0.0", 
   "block_score": "232.0", 
   "ks": "0.9983", 
   "source": "Glyma.20G019300"
  }, 
  {
   "distance": 0.97065, 
   "target": "GRMZM2G410812", 
   "source": "mrna20021"
  }, 
  {
   "distance": 0.28624999999999995, 
   "ka": "0.1113", 
   "target": "16037677", 
   "evalue": "0.0", 
   "block_score": "338.0", 
   "ks": "1.908", 
   "source": "mrna20021"
  }, 
  {
   "distance": 0.18047999999999997, 
   "ka": "0.0796", 
   "target": "Potri.012G124400", 
   "evalue": "0.0", 
   "block_score": "1046.0", 
   "ks": "0.9525", 
   "source": "mrna20021"
  }, 
  {
   "distance": 0.18189, 
   "ka": "0.0793", 
   "target": "GSVIVT01012103001", 
   "evalue": "0.0", 
   "block_score": "1245.0", 
   "ks": "0.8883", 
   "source": "mrna20021"
  }, 
  {
   "distance": 0.46973, 
   "target": "GRMZM2G180150", 
   "source": "mrna20021"
  }, 
  {
   "distance": 0.18902999999999998, 
   "ka": "0.053", 
   "target": "29840.m000608", 
   "evalue": "0.0", 
   "block_score": "265.0", 
   "ks": "1.1193", 
   "source": "mrna20021"
  }, 
  {
   "distance": 0.35429, 
   "target": "Potri.015G124000", 
   "source": "mrna20021"
  }, 
  {
   "distance": 0.28534000000000004, 
   "ka": "0.1201", 
   "target": "GSVIVT01012103001", 
   "evalue": "0.0", 
   "block_score": "436.0", 
   "ks": "1.4724", 
   "source": "16037677"
  }, 
  {
   "distance": 0.24083999999999997, 
   "target": "29840.m000608", 
   "source": "16037677"
  }, 
  {
   "distance": 0.23228999999999997, 
   "target": "Potri.012G124400", 
   "source": "16037677"
  }, 
  {
   "distance": 1.0740999999999998, 
   "target": "GRMZM2G410812", 
   "source": "16037677"
  }, 
  {
   "distance": 0.5731799999999999, 
   "target": "GRMZM2G180150", 
   "source": "16037677"
  }, 
  {
   "distance": 0.40609999999999996, 
   "target": "Potri.015G124000", 
   "source": "16037677"
  }, 
  {
   "distance": 0.07861, 
   "target": "29840.m000608", 
   "source": "Potri.012G124400"
  }, 
  {
   "distance": 0.9683299999999999, 
   "target": "GRMZM2G410812", 
   "source": "Potri.012G124400"
  }, 
  {
   "distance": 0.46741, 
   "target": "GRMZM2G180150", 
   "source": "Potri.012G124400"
  }, 
  {
   "distance": 0.21769, 
   "target": "Potri.015G124000", 
   "source": "Potri.012G124400"
  }, 
  {
   "distance": 0.17956999999999998, 
   "ka": "0.0752", 
   "target": "GSVIVT01012103001", 
   "evalue": "0.0", 
   "block_score": "303.0", 
   "ks": "0.8079", 
   "source": "Potri.012G124400"
  }, 
  {
   "distance": 0.9768799999999999, 
   "target": "29840.m000608", 
   "source": "GRMZM2G410812"
  }, 
  {
   "distance": 0.6552200000000001, 
   "target": "GRMZM2G180150", 
   "source": "GRMZM2G410812"
  }, 
  {
   "distance": 1.1421400000000002, 
   "target": "Potri.015G124000", 
   "source": "GRMZM2G410812"
  }, 
  {
   "distance": 0.9382199999999999, 
   "target": "GSVIVT01012103001", 
   "source": "GRMZM2G410812"
  }, 
  {
   "distance": 0.47596, 
   "target": "29840.m000608", 
   "source": "GRMZM2G180150"
  }, 
  {
   "distance": 0.6412199999999999, 
   "target": "Potri.015G124000", 
   "source": "GRMZM2G180150"
  }, 
  {
   "distance": 0.4373, 
   "target": "GSVIVT01012103001", 
   "source": "GRMZM2G180150"
  }, 
  {
   "distance": 0.25242, 
   "target": "Potri.015G124000", 
   "source": "29840.m000608"
  }, 
  {
   "distance": 0.18811999999999998, 
   "ka": "0.056", 
   "target": "GSVIVT01012103001", 
   "evalue": "0.0", 
   "block_score": "269.0", 
   "ks": "0.7081", 
   "source": "29840.m000608"
  }, 
  {
   "distance": 0.35337999999999997, 
   "target": "GSVIVT01012103001", 
   "source": "Potri.015G124000"
  }
 ]
}